Lab1/div_checker/div_checker.v
`define odd 1'b0
`define even 1'b1
`define oddRmdr 1
`define evenRmdr 2

module div_checker(
    input wire [7:0] inNumber,
    output reg outValue
);

    reg [1:0] remainder;
    reg parity; // parity of power of two (0 - odd, 1 - even)
    genvar i;
    generate for(i = 0; i < 8; i = i + 1)
    always @(inNumber) begin

        remainder = 0;
        parity = `odd;
        // if odd remainder is 1 else (-1)
        begin : loop

            if(inNumber[i]) begin
                if(parity == `odd) begin
                    remainder = remainder + `oddRmdr;
                end
                else begin
                    if(remainder == 2)  // problem with overflow
                        remainder = 1;
                    else
                        remainder = remainder + `evenRmdr;
                end
                if(remainder == 3)
                    remainder = 0;
            end
            parity = ~parity;
        end

        if(remainder == 0)
            assign outValue = 1;
        else
            assign outValue = 0;
    end
    endgenerate

endmodule

// хз мб там есть операция изьятия остатка из деления любых целых чисел,
// но мне показалось, что раз нам дана именно тройка то можно использовать
// математику для написания эффективного алгоритма, хоть он и может быть
// менее читаемым

Lab1/div_checker/test_module.v
`include "div_checker.v"

module test_module;

    reg [7:0] inNumber = 0;
    wire outValue;

    always begin
        #10 inNumber = inNumber+ 1;
    end

    div_checker div_checker1(inNumber, outValue);

    integer i = 0;
    always @(inNumber) begin //перебор остатков деления на 3
        #5
        if((i == 0 && outValue) || (i != 0 && ~outValue)) $display("Success!");
        else $display("Jopa!");
        i = i + 1;
        if(i == 3) i = 0;
    end

    initial begin
        $dumpfile("test.vcd");
        $dumpvars(0, test_module);
    end

    initial begin
        #500 $finish();
    end

    initial begin
        $monitor(inNumber,, outValue);
    end


endmodule

Lab1/div_checker/test.vcd
$date
	Mon May  8 01:37:21 2023
$end
$version
	Icarus Verilog
$end
$timescale
	1s
$end
$scope module test_module $end
$var wire 1 ! outValue $end
$var reg 8 " inNumber [7:0] $end
$var integer 32 # i [31:0] $end
$scope module div_checker1 $end
$var wire 8 $ inNumber [7:0] $end
$var reg 1 ! outValue $end
$var reg 1 % parity $end
$var reg 2 & remainder [1:0] $end
$scope begin genblk1[0] $end
$scope begin loop $end
$upscope $end
$upscope $end
$scope begin genblk1[1] $end
$scope begin loop $end
$upscope $end
$upscope $end
$scope begin genblk1[2] $end
$scope begin loop $end
$upscope $end
$upscope $end
$scope begin genblk1[3] $end
$scope begin loop $end
$upscope $end
$upscope $end
$scope begin genblk1[4] $end
$scope begin loop $end
$upscope $end
$upscope $end
$scope begin genblk1[5] $end
$scope begin loop $end
$upscope $end
$upscope $end
$scope begin genblk1[6] $end
$scope begin loop $end
$upscope $end
$upscope $end
$scope begin genblk1[7] $end
$scope begin loop $end
$upscope $end
$upscope $end
$upscope $end
$upscope $end
$enddefinitions $end
#0
$dumpvars
b0 &
0%
b0 $
b0 #
b0 "
1!
$end
#5
b1 #
#10
0!
b10 &
0%
b1 "
b1 $
#15
b10 #
#20
0!
0%
b1 &
b10 "
b10 $
#25
b0 #
#30
1!
0%
b0 &
b11 "
b11 $
#35
b1 #
#40
0!
b10 &
0%
b100 "
b100 $
#45
b10 #
#50
0!
0%
b1 &
b101 "
b101 $
#55
b0 #
#60
1!
0%
b0 &
b110 "
b110 $
#65
b1 #
#70
0!
b10 &
0%
b111 "
b111 $
#75
b10 #
#80
0!
0%
b1 &
b1000 "
b1000 $
#85
b0 #
#90
1!
0%
b0 &
b1001 "
b1001 $
#95
b1 #
#100
0!
b10 &
0%
b1010 "
b1010 $
#105
b10 #
#110
0!
0%
b1 &
b1011 "
b1011 $
#115
b0 #
#120
1!
0%
b0 &
b1100 "
b1100 $
#125
b1 #
#130
0!
b10 &
0%
b1101 "
b1101 $
#135
b10 #
#140
0!
0%
b1 &
b1110 "
b1110 $
#145
b0 #
#150
1!
0%
b0 &
b1111 "
b1111 $
#155
b1 #
#160
0!
b10 &
0%
b10000 "
b10000 $
#165
b10 #
#170
0!
0%
b1 &
b10001 "
b10001 $
#175
b0 #
#180
1!
0%
b0 &
b10010 "
b10010 $
#185
b1 #
#190
0!
b10 &
0%
b10011 "
b10011 $
#195
b10 #
#200
0!
0%
b1 &
b10100 "
b10100 $
#205
b0 #
#210
1!
0%
b0 &
b10101 "
b10101 $
#215
b1 #
#220
0!
b10 &
0%
b10110 "
b10110 $
#225
b10 #
#230
0!
0%
b1 &
b10111 "
b10111 $
#235
b0 #
#240
1!
0%
b0 &
b11000 "
b11000 $
#245
b1 #
#250
0!
b10 &
0%
b11001 "
b11001 $
#255
b10 #
#260
0!
0%
b1 &
b11010 "
b11010 $
#265
b0 #
#270
1!
0%
b0 &
b11011 "
b11011 $
#275
b1 #
#280
0!
b10 &
0%
b11100 "
b11100 $
#285
b10 #
#290
0!
0%
b1 &
b11101 "
b11101 $
#295
b0 #
#300
1!
0%
b0 &
b11110 "
b11110 $
#305
b1 #
#310
0!
b10 &
0%
b11111 "
b11111 $
#315
b10 #
#320
0!
0%
b1 &
b100000 "
b100000 $
#325
b0 #
#330
1!
0%
b0 &
b100001 "
b100001 $
#335
b1 #
#340
0!
b10 &
0%
b100010 "
b100010 $
#345
b10 #
#350
0!
0%
b1 &
b100011 "
b100011 $
#355
b0 #
#360
1!
0%
b0 &
b100100 "
b100100 $
#365
b1 #
#370
0!
b10 &
0%
b100101 "
b100101 $
#375
b10 #
#380
0!
0%
b1 &
b100110 "
b100110 $
#385
b0 #
#390
1!
0%
b0 &
b100111 "
b100111 $
#395
b1 #
#400
0!
b10 &
0%
b101000 "
b101000 $
#405
b10 #
#410
0!
0%
b1 &
b101001 "
b101001 $
#415
b0 #
#420
1!
0%
b0 &
b101010 "
b101010 $
#425
b1 #
#430
0!
b10 &
0%
b101011 "
b101011 $
#435
b10 #
#440
0!
0%
b1 &
b101100 "
b101100 $
#445
b0 #
#450
1!
0%
b0 &
b101101 "
b101101 $
#455
b1 #
#460
0!
b10 &
0%
b101110 "
b101110 $
#465
b10 #
#470
0!
0%
b1 &
b101111 "
b101111 $
#475
b0 #
#480
1!
0%
b0 &
b110000 "
b110000 $
#485
b1 #
#490
0!
b10 &
0%
b110001 "
b110001 $
#495
b10 #
#500
0!
0%
b1 &
b110010 "
b110010 $
