Lab1/div_checker/div_checker.v
module div_checker(
    input wire [7:0] inNumber,
    output wire outValue
);

    wire [2:0] count_odd;
    wire [2:0] count_even;

    assign count_odd = inNumber[0] + inNumber[2] + inNumber[4] + inNumber[6];
    assign count_even = inNumber[1] + inNumber[3] + inNumber[5] + inNumber[7];

    wire  [4:0] reminder;

    assign reminder = count_odd + 2 * count_even;

    assign outValue = (reminder == 0 || reminder == 3 || reminder == 6 || reminder == 9 || reminder == 12) ? 1 : 0;

endmodule

Lab1/div_checker/test_module.v
`include "div_checker.v"

module test_module;

    reg [7:0] inNumber = 0;
    wire outValue;

    always begin
        #10 inNumber = inNumber + 1;
    end

    div_checker div_checker1(inNumber, outValue);

    integer status = 0;
    always @(inNumber) begin //перебор остатков деления на 3
        #5
        if(inNumber % 3 == 0) $display("Success!");
        else begin
            $display("Jopa!");
            status = -1;
        end
    end

    initial begin
        $dumpfile("test.vcd");
        $dumpvars(0, test_module);
    end

    initial begin
        #3000
        if(status == -1)
            $display("There are errors!!!");
        else if(status == 0)
            $display("норм");
        $finish();
    end

    initial begin
        $monitor(inNumber,, outValue);
    end


endmodule

Lab1/div_checker/test.vcd
$date
	Mon May  8 20:12:23 2023
$end
$version
	Icarus Verilog
$end
$timescale
	1s
$end
$scope module test_module $end
$var wire 1 ! outValue $end
$var reg 8 " inNumber [7:0] $end
$var integer 32 # status [31:0] $end
$scope module div_checker1 $end
$var wire 8 $ inNumber [7:0] $end
$var wire 5 % reminder [4:0] $end
$var wire 1 ! outValue $end
$var wire 3 & count_odd [2:0] $end
$var wire 3 ' count_even [2:0] $end
$upscope $end
$upscope $end
$enddefinitions $end
#0
$dumpvars
b0 '
b0 &
b0 %
b0 $
b0 #
b0 "
1!
$end
#10
0!
b1 %
b1 &
b1 "
b1 $
#15
b11111111111111111111111111111111 #
#20
b0 &
b10 %
b1 '
b10 "
b10 $
#30
1!
b11 %
b1 &
b11 "
b11 $
#40
0!
b1 &
b1 %
b0 '
b100 "
b100 $
#50
b10 %
b10 &
b101 "
b101 $
#60
1!
b1 &
b11 %
b1 '
b110 "
b110 $
#70
0!
b100 %
b10 &
b111 "
b111 $
#80
b0 &
b10 %
b1 '
b1000 "
b1000 $
#90
1!
b11 %
b1 &
b1001 "
b1001 $
#100
0!
b0 &
b100 %
b10 '
b1010 "
b1010 $
#110
b101 %
b1 &
b1011 "
b1011 $
#120
1!
b1 &
b11 %
b1 '
b1100 "
b1100 $
#130
0!
b100 %
b10 &
b1101 "
b1101 $
#140
b1 &
b101 %
b10 '
b1110 "
b1110 $
#150
1!
b110 %
b10 &
b1111 "
b1111 $
#160
0!
b1 &
b1 %
b0 '
b10000 "
b10000 $
#170
b10 %
b10 &
b10001 "
b10001 $
#180
1!
b1 &
b11 %
b1 '
b10010 "
b10010 $
#190
0!
b100 %
b10 &
b10011 "
b10011 $
#200
b10 &
b10 %
b0 '
b10100 "
b10100 $
#210
1!
b11 %
b11 &
b10101 "
b10101 $
#220
0!
b10 &
b100 %
b1 '
b10110 "
b10110 $
#230
b101 %
b11 &
b10111 "
b10111 $
#240
1!
b1 &
b11 %
b1 '
b11000 "
b11000 $
#250
0!
b100 %
b10 &
b11001 "
b11001 $
#260
b1 &
b101 %
b10 '
b11010 "
b11010 $
#270
1!
b110 %
b10 &
b11011 "
b11011 $
#280
0!
b10 &
b100 %
b1 '
b11100 "
b11100 $
#290
b101 %
b11 &
b11101 "
b11101 $
#300
1!
b10 &
b110 %
b10 '
b11110 "
b11110 $
#310
0!
b111 %
b11 &
b11111 "
b11111 $
#320
b0 &
b10 %
b1 '
b100000 "
b100000 $
#330
1!
b11 %
b1 &
b100001 "
b100001 $
#340
0!
b0 &
b100 %
b10 '
b100010 "
b100010 $
#350
b101 %
b1 &
b100011 "
b100011 $
#360
1!
b1 &
b11 %
b1 '
b100100 "
b100100 $
#370
0!
b100 %
b10 &
b100101 "
b100101 $
#380
b1 &
b101 %
b10 '
b100110 "
b100110 $
#390
1!
b110 %
b10 &
b100111 "
b100111 $
#400
0!
b0 &
b100 %
b10 '
b101000 "
b101000 $
#410
b101 %
b1 &
b101001 "
b101001 $
#420
1!
b0 &
b110 %
b11 '
b101010 "
b101010 $
#430
0!
b111 %
b1 &
b101011 "
b101011 $
#440
b1 &
b101 %
b10 '
b101100 "
b101100 $
#450
1!
b110 %
b10 &
b101101 "
b101101 $
#460
0!
b1 &
b111 %
b11 '
b101110 "
b101110 $
#470
b1000 %
b10 &
b101111 "
b101111 $
#480
1!
b1 &
b11 %
b1 '
b110000 "
b110000 $
#490
0!
b100 %
b10 &
b110001 "
b110001 $
#500
b1 &
b101 %
b10 '
b110010 "
b110010 $
#510
1!
b110 %
b10 &
b110011 "
b110011 $
#520
0!
b10 &
b100 %
b1 '
b110100 "
b110100 $
#530
b101 %
b11 &
b110101 "
b110101 $
#540
1!
b10 &
b110 %
b10 '
b110110 "
b110110 $
#550
0!
b111 %
b11 &
b110111 "
b110111 $
#560
b1 &
b101 %
b10 '
b111000 "
b111000 $
#570
1!
b110 %
b10 &
b111001 "
b111001 $
#580
0!
b1 &
b111 %
b11 '
b111010 "
b111010 $
#590
b1000 %
b10 &
b111011 "
b111011 $
#600
1!
b10 &
b110 %
b10 '
b111100 "
b111100 $
#610
0!
b111 %
b11 &
b111101 "
b111101 $
#620
b10 &
b1000 %
b11 '
b111110 "
b111110 $
#630
1!
b1001 %
b11 &
b111111 "
b111111 $
#640
0!
b1 &
b1 %
b0 '
b1000000 "
b1000000 $
#650
b10 %
b10 &
b1000001 "
b1000001 $
#660
1!
b1 &
b11 %
b1 '
b1000010 "
b1000010 $
#670
0!
b100 %
b10 &
b1000011 "
b1000011 $
#680
b10 &
b10 %
b0 '
b1000100 "
b1000100 $
#690
1!
b11 %
b11 &
b1000101 "
b1000101 $
#700
0!
b10 &
b100 %
b1 '
b1000110 "
b1000110 $
#710
b101 %
b11 &
b1000111 "
b1000111 $
#720
1!
b1 &
b11 %
b1 '
b1001000 "
b1001000 $
#730
0!
b100 %
b10 &
b1001001 "
b1001001 $
#740
b1 &
b101 %
b10 '
b1001010 "
b1001010 $
#750
1!
b110 %
b10 &
b1001011 "
b1001011 $
#760
0!
b10 &
b100 %
b1 '
b1001100 "
b1001100 $
#770
b101 %
b11 &
b1001101 "
b1001101 $
#780
1!
b10 &
b110 %
b10 '
b1001110 "
b1001110 $
#790
0!
b111 %
b11 &
b1001111 "
b1001111 $
#800
b10 &
b10 %
b0 '
b1010000 "
b1010000 $
#810
1!
b11 %
b11 &
b1010001 "
b1010001 $
#820
0!
b10 &
b100 %
b1 '
b1010010 "
b1010010 $
#830
b101 %
b11 &
b1010011 "
b1010011 $
#840
1!
b11 &
b11 %
b0 '
b1010100 "
b1010100 $
#850
0!
b100 %
b100 &
b1010101 "
b1010101 $
#860
b11 &
b101 %
b1 '
b1010110 "
b1010110 $
#870
1!
b110 %
b100 &
b1010111 "
b1010111 $
#880
0!
b10 &
b100 %
b1 '
b1011000 "
b1011000 $
#890
b101 %
b11 &
b1011001 "
b1011001 $
#900
1!
b10 &
b110 %
b10 '
b1011010 "
b1011010 $
#910
0!
b111 %
b11 &
b1011011 "
b1011011 $
#920
b11 &
b101 %
b1 '
b1011100 "
b1011100 $
#930
1!
b110 %
b100 &
b1011101 "
b1011101 $
#940
0!
b11 &
b111 %
b10 '
b1011110 "
b1011110 $
#950
b1000 %
b100 &
b1011111 "
b1011111 $
#960
1!
b1 &
b11 %
b1 '
b1100000 "
b1100000 $
#970
0!
b100 %
b10 &
b1100001 "
b1100001 $
#980
b1 &
b101 %
b10 '
b1100010 "
b1100010 $
#990
1!
b110 %
b10 &
b1100011 "
b1100011 $
#1000
0!
b10 &
b100 %
b1 '
b1100100 "
b1100100 $
#1010
b101 %
b11 &
b1100101 "
b1100101 $
#1020
1!
b10 &
b110 %
b10 '
b1100110 "
b1100110 $
#1030
0!
b111 %
b11 &
b1100111 "
b1100111 $
#1040
b1 &
b101 %
b10 '
b1101000 "
b1101000 $
#1050
1!
b110 %
b10 &
b1101001 "
b1101001 $
#1060
0!
b1 &
b111 %
b11 '
b1101010 "
b1101010 $
#1070
b1000 %
b10 &
b1101011 "
b1101011 $
#1080
1!
b10 &
b110 %
b10 '
b1101100 "
b1101100 $
#1090
0!
b111 %
b11 &
b1101101 "
b1101101 $
#1100
b10 &
b1000 %
b11 '
b1101110 "
b1101110 $
#1110
1!
b1001 %
b11 &
b1101111 "
b1101111 $
#1120
0!
b10 &
b100 %
b1 '
b1110000 "
b1110000 $
#1130
b101 %
b11 &
b1110001 "
b1110001 $
#1140
1!
b10 &
b110 %
b10 '
b1110010 "
b1110010 $
#1150
0!
b111 %
b11 &
b1110011 "
b1110011 $
#1160
b11 &
b101 %
b1 '
b1110100 "
b1110100 $
#1170
1!
b110 %
b100 &
b1110101 "
b1110101 $
#1180
0!
b11 &
b111 %
b10 '
b1110110 "
b1110110 $
#1190
b1000 %
b100 &
b1110111 "
b1110111 $
#1200
1!
b10 &
b110 %
b10 '
b1111000 "
b1111000 $
#1210
0!
b111 %
b11 &
b1111001 "
b1111001 $
#1220
b10 &
b1000 %
b11 '
b1111010 "
b1111010 $
#1230
1!
b1001 %
b11 &
b1111011 "
b1111011 $
#1240
0!
b11 &
b111 %
b10 '
b1111100 "
b1111100 $
#1250
b1000 %
b100 &
b1111101 "
b1111101 $
#1260
1!
b11 &
b1001 %
b11 '
b1111110 "
b1111110 $
#1270
0!
b1010 %
b100 &
b1111111 "
b1111111 $
#1280
b0 &
b10 %
b1 '
b10000000 "
b10000000 $
#1290
1!
b11 %
b1 &
b10000001 "
b10000001 $
#1300
0!
b0 &
b100 %
b10 '
b10000010 "
b10000010 $
#1310
b101 %
b1 &
b10000011 "
b10000011 $
#1320
1!
b1 &
b11 %
b1 '
b10000100 "
b10000100 $
#1330
0!
b100 %
b10 &
b10000101 "
b10000101 $
#1340
b1 &
b101 %
b10 '
b10000110 "
b10000110 $
#1350
1!
b110 %
b10 &
b10000111 "
b10000111 $
#1360
0!
b0 &
b100 %
b10 '
b10001000 "
b10001000 $
#1370
b101 %
b1 &
b10001001 "
b10001001 $
#1380
1!
b0 &
b110 %
b11 '
b10001010 "
b10001010 $
#1390
0!
b111 %
b1 &
b10001011 "
b10001011 $
#1400
b1 &
b101 %
b10 '
b10001100 "
b10001100 $
#1410
1!
b110 %
b10 &
b10001101 "
b10001101 $
#1420
0!
b1 &
b111 %
b11 '
b10001110 "
b10001110 $
#1430
b1000 %
b10 &
b10001111 "
b10001111 $
#1440
1!
b1 &
b11 %
b1 '
b10010000 "
b10010000 $
#1450
0!
b100 %
b10 &
b10010001 "
b10010001 $
#1460
b1 &
b101 %
b10 '
b10010010 "
b10010010 $
#1470
1!
b110 %
b10 &
b10010011 "
b10010011 $
#1480
0!
b10 &
b100 %
b1 '
b10010100 "
b10010100 $
#1490
b101 %
b11 &
b10010101 "
b10010101 $
#1500
1!
b10 &
b110 %
b10 '
b10010110 "
b10010110 $
#1510
0!
b111 %
b11 &
b10010111 "
b10010111 $
#1520
b1 &
b101 %
b10 '
b10011000 "
b10011000 $
#1530
1!
b110 %
b10 &
b10011001 "
b10011001 $
#1540
0!
b1 &
b111 %
b11 '
b10011010 "
b10011010 $
#1550
b1000 %
b10 &
b10011011 "
b10011011 $
#1560
1!
b10 &
b110 %
b10 '
b10011100 "
b10011100 $
#1570
0!
b111 %
b11 &
b10011101 "
b10011101 $
#1580
b10 &
b1000 %
b11 '
b10011110 "
b10011110 $
#1590
1!
b1001 %
b11 &
b10011111 "
b10011111 $
#1600
0!
b0 &
b100 %
b10 '
b10100000 "
b10100000 $
#1610
b101 %
b1 &
b10100001 "
b10100001 $
#1620
1!
b0 &
b110 %
b11 '
b10100010 "
b10100010 $
#1630
0!
b111 %
b1 &
b10100011 "
b10100011 $
#1640
b1 &
b101 %
b10 '
b10100100 "
b10100100 $
#1650
1!
b110 %
b10 &
b10100101 "
b10100101 $
#1660
0!
b1 &
b111 %
b11 '
b10100110 "
b10100110 $
#1670
b1000 %
b10 &
b10100111 "
b10100111 $
#1680
1!
b0 &
b110 %
b11 '
b10101000 "
b10101000 $
#1690
0!
b111 %
b1 &
b10101001 "
b10101001 $
#1700
b0 &
b1000 %
b100 '
b10101010 "
b10101010 $
#1710
1!
b1001 %
b1 &
b10101011 "
b10101011 $
#1720
0!
b1 &
b111 %
b11 '
b10101100 "
b10101100 $
#1730
b1000 %
b10 &
b10101101 "
b10101101 $
#1740
1!
b1 &
b1001 %
b100 '
b10101110 "
b10101110 $
#1750
0!
b1010 %
b10 &
b10101111 "
b10101111 $
#1760
b1 &
b101 %
b10 '
b10110000 "
b10110000 $
#1770
1!
b110 %
b10 &
b10110001 "
b10110001 $
#1780
0!
b1 &
b111 %
b11 '
b10110010 "
b10110010 $
#1790
b1000 %
b10 &
b10110011 "
b10110011 $
#1800
1!
b10 &
b110 %
b10 '
b10110100 "
b10110100 $
#1810
0!
b111 %
b11 &
b10110101 "
b10110101 $
#1820
b10 &
b1000 %
b11 '
b10110110 "
b10110110 $
#1830
1!
b1001 %
b11 &
b10110111 "
b10110111 $
#1840
0!
b1 &
b111 %
b11 '
b10111000 "
b10111000 $
#1850
b1000 %
b10 &
b10111001 "
b10111001 $
#1860
1!
b1 &
b1001 %
b100 '
b10111010 "
b10111010 $
#1870
0!
b1010 %
b10 &
b10111011 "
b10111011 $
#1880
b10 &
b1000 %
b11 '
b10111100 "
b10111100 $
#1890
1!
b1001 %
b11 &
b10111101 "
b10111101 $
#1900
0!
b10 &
b1010 %
b100 '
b10111110 "
b10111110 $
#1910
b1011 %
b11 &
b10111111 "
b10111111 $
#1920
1!
b1 &
b11 %
b1 '
b11000000 "
b11000000 $
#1930
0!
b100 %
b10 &
b11000001 "
b11000001 $
#1940
b1 &
b101 %
b10 '
b11000010 "
b11000010 $
#1950
1!
b110 %
b10 &
b11000011 "
b11000011 $
#1960
0!
b10 &
b100 %
b1 '
b11000100 "
b11000100 $
#1970
b101 %
b11 &
b11000101 "
b11000101 $
#1980
1!
b10 &
b110 %
b10 '
b11000110 "
b11000110 $
#1990
0!
b111 %
b11 &
b11000111 "
b11000111 $
#2000
b1 &
b101 %
b10 '
b11001000 "
b11001000 $
#2010
1!
b110 %
b10 &
b11001001 "
b11001001 $
#2020
0!
b1 &
b111 %
b11 '
b11001010 "
b11001010 $
#2030
b1000 %
b10 &
b11001011 "
b11001011 $
#2040
1!
b10 &
b110 %
b10 '
b11001100 "
b11001100 $
#2050
0!
b111 %
b11 &
b11001101 "
b11001101 $
#2060
b10 &
b1000 %
b11 '
b11001110 "
b11001110 $
#2070
1!
b1001 %
b11 &
b11001111 "
b11001111 $
#2080
0!
b10 &
b100 %
b1 '
b11010000 "
b11010000 $
#2090
b101 %
b11 &
b11010001 "
b11010001 $
#2100
1!
b10 &
b110 %
b10 '
b11010010 "
b11010010 $
#2110
0!
b111 %
b11 &
b11010011 "
b11010011 $
#2120
b11 &
b101 %
b1 '
b11010100 "
b11010100 $
#2130
1!
b110 %
b100 &
b11010101 "
b11010101 $
#2140
0!
b11 &
b111 %
b10 '
b11010110 "
b11010110 $
#2150
b1000 %
b100 &
b11010111 "
b11010111 $
#2160
1!
b10 &
b110 %
b10 '
b11011000 "
b11011000 $
#2170
0!
b111 %
b11 &
b11011001 "
b11011001 $
#2180
b10 &
b1000 %
b11 '
b11011010 "
b11011010 $
#2190
1!
b1001 %
b11 &
b11011011 "
b11011011 $
#2200
0!
b11 &
b111 %
b10 '
b11011100 "
b11011100 $
#2210
b1000 %
b100 &
b11011101 "
b11011101 $
#2220
1!
b11 &
b1001 %
b11 '
b11011110 "
b11011110 $
#2230
0!
b1010 %
b100 &
b11011111 "
b11011111 $
#2240
b1 &
b101 %
b10 '
b11100000 "
b11100000 $
#2250
1!
b110 %
b10 &
b11100001 "
b11100001 $
#2260
0!
b1 &
b111 %
b11 '
b11100010 "
b11100010 $
#2270
b1000 %
b10 &
b11100011 "
b11100011 $
#2280
1!
b10 &
b110 %
b10 '
b11100100 "
b11100100 $
#2290
0!
b111 %
b11 &
b11100101 "
b11100101 $
#2300
b10 &
b1000 %
b11 '
b11100110 "
b11100110 $
#2310
1!
b1001 %
b11 &
b11100111 "
b11100111 $
#2320
0!
b1 &
b111 %
b11 '
b11101000 "
b11101000 $
#2330
b1000 %
b10 &
b11101001 "
b11101001 $
#2340
1!
b1 &
b1001 %
b100 '
b11101010 "
b11101010 $
#2350
0!
b1010 %
b10 &
b11101011 "
b11101011 $
#2360
b10 &
b1000 %
b11 '
b11101100 "
b11101100 $
#2370
1!
b1001 %
b11 &
b11101101 "
b11101101 $
#2380
0!
b10 &
b1010 %
b100 '
b11101110 "
b11101110 $
#2390
b1011 %
b11 &
b11101111 "
b11101111 $
#2400
1!
b10 &
b110 %
b10 '
b11110000 "
b11110000 $
#2410
0!
b111 %
b11 &
b11110001 "
b11110001 $
#2420
b10 &
b1000 %
b11 '
b11110010 "
b11110010 $
#2430
1!
b1001 %
b11 &
b11110011 "
b11110011 $
#2440
0!
b11 &
b111 %
b10 '
b11110100 "
b11110100 $
#2450
b1000 %
b100 &
b11110101 "
b11110101 $
#2460
1!
b11 &
b1001 %
b11 '
b11110110 "
b11110110 $
#2470
0!
b1010 %
b100 &
b11110111 "
b11110111 $
#2480
b10 &
b1000 %
b11 '
b11111000 "
b11111000 $
#2490
1!
b1001 %
b11 &
b11111001 "
b11111001 $
#2500
0!
b10 &
b1010 %
b100 '
b11111010 "
b11111010 $
#2510
b1011 %
b11 &
b11111011 "
b11111011 $
#2520
1!
b11 &
b1001 %
b11 '
b11111100 "
b11111100 $
#2530
0!
b1010 %
b100 &
b11111101 "
b11111101 $
#2540
b11 &
b1011 %
b100 '
b11111110 "
b11111110 $
#2550
1!
b1100 %
b100 &
b11111111 "
b11111111 $
#2560
1!
b0 &
b0 %
b0 '
b0 "
b0 $
#2570
0!
b1 %
b1 &
b1 "
b1 $
#2580
b0 &
b10 %
b1 '
b10 "
b10 $
#2590
1!
b11 %
b1 &
b11 "
b11 $
#2600
0!
b1 &
b1 %
b0 '
b100 "
b100 $
#2610
b10 %
b10 &
b101 "
b101 $
#2620
1!
b1 &
b11 %
b1 '
b110 "
b110 $
#2630
0!
b100 %
b10 &
b111 "
b111 $
#2640
b0 &
b10 %
b1 '
b1000 "
b1000 $
#2650
1!
b11 %
b1 &
b1001 "
b1001 $
#2660
0!
b0 &
b100 %
b10 '
b1010 "
b1010 $
#2670
b101 %
b1 &
b1011 "
b1011 $
#2680
1!
b1 &
b11 %
b1 '
b1100 "
b1100 $
#2690
0!
b100 %
b10 &
b1101 "
b1101 $
#2700
b1 &
b101 %
b10 '
b1110 "
b1110 $
#2710
1!
b110 %
b10 &
b1111 "
b1111 $
#2720
0!
b1 &
b1 %
b0 '
b10000 "
b10000 $
#2730
b10 %
b10 &
b10001 "
b10001 $
#2740
1!
b1 &
b11 %
b1 '
b10010 "
b10010 $
#2750
0!
b100 %
b10 &
b10011 "
b10011 $
#2760
b10 &
b10 %
b0 '
b10100 "
b10100 $
#2770
1!
b11 %
b11 &
b10101 "
b10101 $
#2780
0!
b10 &
b100 %
b1 '
b10110 "
b10110 $
#2790
b101 %
b11 &
b10111 "
b10111 $
#2800
1!
b1 &
b11 %
b1 '
b11000 "
b11000 $
#2810
0!
b100 %
b10 &
b11001 "
b11001 $
#2820
b1 &
b101 %
b10 '
b11010 "
b11010 $
#2830
1!
b110 %
b10 &
b11011 "
b11011 $
#2840
0!
b10 &
b100 %
b1 '
b11100 "
b11100 $
#2850
b101 %
b11 &
b11101 "
b11101 $
#2860
1!
b10 &
b110 %
b10 '
b11110 "
b11110 $
#2870
0!
b111 %
b11 &
b11111 "
b11111 $
#2880
b0 &
b10 %
b1 '
b100000 "
b100000 $
#2890
1!
b11 %
b1 &
b100001 "
b100001 $
#2900
0!
b0 &
b100 %
b10 '
b100010 "
b100010 $
#2910
b101 %
b1 &
b100011 "
b100011 $
#2920
1!
b1 &
b11 %
b1 '
b100100 "
b100100 $
#2930
0!
b100 %
b10 &
b100101 "
b100101 $
#2940
b1 &
b101 %
b10 '
b100110 "
b100110 $
#2950
1!
b110 %
b10 &
b100111 "
b100111 $
#2960
0!
b0 &
b100 %
b10 '
b101000 "
b101000 $
#2970
b101 %
b1 &
b101001 "
b101001 $
#2980
1!
b0 &
b110 %
b11 '
b101010 "
b101010 $
#2990
0!
b111 %
b1 &
b101011 "
b101011 $
#3000
b1 &
b101 %
b10 '
b101100 "
b101100 $
