Lab1/decoder/decoder.v
module decoder #(
    parameter BIN_SIZE = 3,
    parameter BOUT_SIZE = 8
)(
    input wire [BIN_SIZE - 1:0] inNumber,
    output wire [BOUT_SIZE - 1:0] outVector
);
    assign outVector = 1'b1 << inNumber;

endmodule

Lab1/decoder/test_module.v
module test_module;

    reg [2:0] inValue;
    wire [7:0] outValue;

    decoder decoder1(inValue, outValue);

    always
    begin
    #10 inValue = inValue + 1;
    end

    initial begin
        inValue = 4'b0;
    end

    initial
        $monitor(inValue,, outValue);

    initial
        #300 $finish();

    initial begin
        $dumpfile("test.vcd");
        $dumpvars(0, test_module); //levels, top-module
    end

endmodule

Lab1/decoder/test.vcd
$date
	Mon May  8 15:21:12 2023
$end
$version
	Icarus Verilog
$end
$timescale
	1s
$end
$scope module test_module $end
$var wire 8 ! outValue [7:0] $end
$var reg 3 " inValue [2:0] $end
$scope module decoder1 $end
$var wire 3 # inNumber [2:0] $end
$var wire 8 $ outVector [7:0] $end
$upscope $end
$upscope $end
$enddefinitions $end
#0
$dumpvars
b1 $
b0 #
b0 "
b1 !
$end
#10
b10 !
b10 $
b1 "
b1 #
#20
b100 !
b100 $
b10 "
b10 #
#30
b1000 !
b1000 $
b11 "
b11 #
#40
b10000 !
b10000 $
b100 "
b100 #
#50
b100000 !
b100000 $
b101 "
b101 #
#60
b1000000 !
b1000000 $
b110 "
b110 #
#70
b10000000 !
b10000000 $
b111 "
b111 #
#80
b1 !
b1 $
b0 "
b0 #
#90
b10 !
b10 $
b1 "
b1 #
#100
b100 !
b100 $
b10 "
b10 #
#110
b1000 !
b1000 $
b11 "
b11 #
#120
b10000 !
b10000 $
b100 "
b100 #
#130
b100000 !
b100000 $
b101 "
b101 #
#140
b1000000 !
b1000000 $
b110 "
b110 #
#150
b10000000 !
b10000000 $
b111 "
b111 #
#160
b1 !
b1 $
b0 "
b0 #
#170
b10 !
b10 $
b1 "
b1 #
#180
b100 !
b100 $
b10 "
b10 #
#190
b1000 !
b1000 $
b11 "
b11 #
#200
b10000 !
b10000 $
b100 "
b100 #
#210
b100000 !
b100000 $
b101 "
b101 #
#220
b1000000 !
b1000000 $
b110 "
b110 #
#230
b10000000 !
b10000000 $
b111 "
b111 #
#240
b1 !
b1 $
b0 "
b0 #
#250
b10 !
b10 $
b1 "
b1 #
#260
b100 !
b100 $
b10 "
b10 #
#270
b1000 !
b1000 $
b11 "
b11 #
#280
b10000 !
b10000 $
b100 "
b100 #
#290
b100000 !
b100000 $
b101 "
b101 #
#300
b1000000 !
b1000000 $
b110 "
b110 #
