Lab1/prioritiezed endecoder/p_encoder.v
module p_encoder (
    input wire [7:0] inVector,
    output reg [2:0] outNumber
);

    integer i; // надеюсь компилятор ее в итоге уберет
    always @(inVector) begin
        outNumber = 7;
        for(i = 7; i > 0 && ~inVector[i]; i = i - 1) //подразумевается, что 1 когда нибудь встретится
            outNumber = i - 1;
    end
endmodule

//наверное здесь подразумевалось что я нафигачу как черт 8 вложенных друг в друга ифов
//или сделаю версию с флагом и последовательными ифами, ща нафигачу без for (просто выше допускаю, что компилятор умный
//и сделает как я хочу чтобы оно в итоге было)

module p_encoder_second (
    input wire [7:0] inVector,
    output reg [2:0] outNumber
);

    reg found;
    genvar i;
    generate for(i = 7; i >= 0; i = i - 1)
    always @(inVector)
    begin
        found = 0;
        begin : loop
            if(inVector[i] && ~found)
            begin
                outNumber <= i;
                    found <= 1;
            end
        end
    end
    endgenerate
endmodule

//ПОЧЕМУ У МЕНЯ ОТ МОИХ ВЫКЛАДОК КОМПИЛЯТОР ЗАВИСАЕТ!!! ! !!!! !? ??!???!?!??!!??!?!?!?!?!??!
//потому что не нужно делать вечные циклы, я в первый раз увидел как саморучно зациклил компилятор
//я даже на верилоге циклил командную строку, с каждым днем все новое дно

Lab1/prioritiezed endecoder/test_module.v
module test_module;

    reg [2:0] inValue;
    wire [7:0] midVector;
    reg [7:0] midVectorChanged;
    wire [2:0] outValue;

    //Если p_encoder реализован правильно но inValue == outValue

    decoder decoder1(inValue, midVector);

    always @(midVector)     //нарисую ка красивые лесенки!
        begin
            midVectorChanged = midVector;
            for(integer i = 0; i < inValue; i++)
                midVectorChanged = midVectorChanged | (1 << i);
        end     //остальные варианты перебирать лень, и так все понятно

    p_encoder p_encoder1(midVectorChanged, outValue);

    initial begin
        inValue = 4'b0;
    end

    always @(inValue)
        begin
            #5
            if(inValue  == outValue)
                $display("Success!");
            else
                $display("Jopa!",, inValue,, outValue);
        end

    always
        begin
            #10 inValue = inValue + 1;
        end

    initial
        $monitor(inValue,, midVector,, outValue);

    initial
        #300 $finish();

    initial begin
        $dumpfile("test.vcd");
        $dumpvars(0, test_module); //levels, top-module
    end

endmodule

module decoder(
    input wire [2:0] inNumber,
    output wire [7:0] outVector
);
    assign outVector = 8'b1 << inNumber;

endmodule

Lab1/prioritiezed endecoder/test.vcd
$date
	Sat May  6 21:40:24 2023
$end
$version
	Icarus Verilog
$end
$timescale
	1s
$end
$scope module test_module $end
$var wire 3 ! outValue [2:0] $end
$var wire 8 " midVector [7:0] $end
$var reg 3 # inValue [2:0] $end
$var reg 8 $ midVectorChanged [7:0] $end
$scope module decoder1 $end
$var wire 3 % inNumber [2:0] $end
$var wire 8 & outVector [7:0] $end
$upscope $end
$scope module p_encoder1 $end
$var wire 8 ' inVector [7:0] $end
$var reg 3 ( outNumber [2:0] $end
$var integer 32 ) i [31:0] $end
$upscope $end
$scope begin $ivl_for_loop0 $end
$var integer 32 * i [31:0] $end
$upscope $end
$upscope $end
$enddefinitions $end
#0
$dumpvars
b0 *
b0 )
b0 (
b1 '
b1 &
b0 %
b1 $
b0 #
b1 "
b0 !
$end
#10
b1 )
b1 !
b1 (
b1 *
b11 $
b11 '
b10 "
b10 &
b1 #
b1 %
#20
b10 )
b10 !
b10 (
b10 *
b111 $
b111 '
b100 "
b100 &
b10 #
b10 %
#30
b11 )
b11 !
b11 (
b11 *
b1111 $
b1111 '
b1000 "
b1000 &
b11 #
b11 %
#40
b100 )
b100 !
b100 (
b100 *
b11111 $
b11111 '
b10000 "
b10000 &
b100 #
b100 %
#50
b101 )
b101 !
b101 (
b101 *
b111111 $
b111111 '
b100000 "
b100000 &
b101 #
b101 %
#60
b110 )
b110 !
b110 (
b110 *
b1111111 $
b1111111 '
b1000000 "
b1000000 &
b110 #
b110 %
#70
b111 )
b111 !
b111 (
b111 *
b11111111 $
b11111111 '
b10000000 "
b10000000 &
b111 #
b111 %
#80
b0 )
b0 !
b0 (
b0 *
b1 $
b1 '
b1 "
b1 &
b0 #
b0 %
#90
b1 )
b1 !
b1 (
b1 *
b11 $
b11 '
b10 "
b10 &
b1 #
b1 %
#100
b10 )
b10 !
b10 (
b10 *
b111 $
b111 '
b100 "
b100 &
b10 #
b10 %
#110
b11 )
b11 !
b11 (
b11 *
b1111 $
b1111 '
b1000 "
b1000 &
b11 #
b11 %
#120
b100 )
b100 !
b100 (
b100 *
b11111 $
b11111 '
b10000 "
b10000 &
b100 #
b100 %
#130
b101 )
b101 !
b101 (
b101 *
b111111 $
b111111 '
b100000 "
b100000 &
b101 #
b101 %
#140
b110 )
b110 !
b110 (
b110 *
b1111111 $
b1111111 '
b1000000 "
b1000000 &
b110 #
b110 %
#150
b111 )
b111 !
b111 (
b111 *
b11111111 $
b11111111 '
b10000000 "
b10000000 &
b111 #
b111 %
#160
b0 )
b0 !
b0 (
b0 *
b1 $
b1 '
b1 "
b1 &
b0 #
b0 %
#170
b1 )
b1 !
b1 (
b1 *
b11 $
b11 '
b10 "
b10 &
b1 #
b1 %
#180
b10 )
b10 !
b10 (
b10 *
b111 $
b111 '
b100 "
b100 &
b10 #
b10 %
#190
b11 )
b11 !
b11 (
b11 *
b1111 $
b1111 '
b1000 "
b1000 &
b11 #
b11 %
#200
b100 )
b100 !
b100 (
b100 *
b11111 $
b11111 '
b10000 "
b10000 &
b100 #
b100 %
#210
b101 )
b101 !
b101 (
b101 *
b111111 $
b111111 '
b100000 "
b100000 &
b101 #
b101 %
#220
b110 )
b110 !
b110 (
b110 *
b1111111 $
b1111111 '
b1000000 "
b1000000 &
b110 #
b110 %
#230
b111 )
b111 !
b111 (
b111 *
b11111111 $
b11111111 '
b10000000 "
b10000000 &
b111 #
b111 %
#240
b0 )
b0 !
b0 (
b0 *
b1 $
b1 '
b1 "
b1 &
b0 #
b0 %
#250
b1 )
b1 !
b1 (
b1 *
b11 $
b11 '
b10 "
b10 &
b1 #
b1 %
#260
b10 )
b10 !
b10 (
b10 *
b111 $
b111 '
b100 "
b100 &
b10 #
b10 %
#270
b11 )
b11 !
b11 (
b11 *
b1111 $
b1111 '
b1000 "
b1000 &
b11 #
b11 %
#280
b100 )
b100 !
b100 (
b100 *
b11111 $
b11111 '
b10000 "
b10000 &
b100 #
b100 %
#290
b101 )
b101 !
b101 (
b101 *
b111111 $
b111111 '
b100000 "
b100000 &
b101 #
b101 %
#300
b110 )
b110 !
b110 (
b110 *
b1111111 $
b1111111 '
b1000000 "
b1000000 &
b110 #
b110 %
