Lab2/homework/My-clk-divider/my_clk_div.v
module my_clk_div( //крутые челики сразу общий вариант делителя делают B)

    input wire rst,
    input wire clk,
    input wire [7:0] divCountIn,
    output reg div
);

    reg [7:0] divReg;
    reg [7:0] divCount;

    always @(clk) begin
        if(rst) begin
            divCount <= divCountIn;
            divReg <= 0;
            div <= 0;
        end
        else begin
            divReg = divReg + 1;
        end

        if(divReg == divCount) begin
            divReg = 0;
            div = ~div;
        end
    end

endmodule

Lab2/homework/My-clk-divider/test.v
`include "my_clk_div.v"

module test;
    //construction of test module
    reg clk;
    initial begin
        clk <= 0;
    end

    reg reset;
    initial begin
        reset <= 0;
        @(posedge clk);
        reset <= 1;
        @(posedge clk);
        reset <= 0;

        repeat(2) begin
            #380
            reset <= 0;
            @(posedge clk);
            reset <= 1;
            @(posedge clk);
            reset <= 0;
        end
    end

    reg [7:0] divCountIn;
    initial begin
        divCountIn <= 8'd5;
        #400 divCountIn <= 8'd6;
        #400 divCountIn <= 8'd7;
    end

    always begin
        #10 clk = ~clk;
    end

    //module itself
    wire div;
    my_clk_div my_clk_div1(reset, clk, divCountIn, div);

    //dump settings
    initial begin
        $monitor(reset,, clk,, divCountIn,, div);
    end

    initial begin
        $dumpfile("test.vcd");
        $dumpvars(0, test);
    end

    initial begin
        #1200 $finish();
    end

endmodule

Lab2/homework/My-clk-divider/test.vcd
$date
	Sat May  6 22:57:59 2023
$end
$version
	Icarus Verilog
$end
$timescale
	1s
$end
$scope module test $end
$var wire 1 ! div $end
$var reg 1 " clk $end
$var reg 8 # divCountIn [7:0] $end
$var reg 1 $ reset $end
$scope module my_clk_div1 $end
$var wire 1 " clk $end
$var wire 8 % divCountIn [7:0] $end
$var wire 1 $ rst $end
$var reg 1 ! div $end
$var reg 8 & divCount [7:0] $end
$var reg 8 ' divReg [7:0] $end
$upscope $end
$upscope $end
$enddefinitions $end
#0
$dumpvars
bx '
bx &
b101 %
0$
b101 #
0"
x!
$end
#10
1$
1"
#20
0!
b0 '
b101 &
0"
#30
0$
1"
#40
b1 '
0"
#50
b10 '
1"
#60
b11 '
0"
#70
b100 '
1"
#80
1!
b0 '
0"
#90
b1 '
1"
#100
b10 '
0"
#110
b11 '
1"
#120
b100 '
0"
#130
0!
b0 '
1"
#140
b1 '
0"
#150
b10 '
1"
#160
b11 '
0"
#170
b100 '
1"
#180
1!
b0 '
0"
#190
b1 '
1"
#200
b10 '
0"
#210
b11 '
1"
#220
b100 '
0"
#230
0!
b0 '
1"
#240
b1 '
0"
#250
b10 '
1"
#260
b11 '
0"
#270
b100 '
1"
#280
1!
b0 '
0"
#290
b1 '
1"
#300
b10 '
0"
#310
b11 '
1"
#320
b100 '
0"
#330
0!
b0 '
1"
#340
b1 '
0"
#350
b10 '
1"
#360
b11 '
0"
#370
b100 '
1"
#380
1!
b0 '
0"
#390
b1 '
1"
#400
b110 #
b110 %
b10 '
0"
#410
1$
b11 '
1"
#420
0!
b0 '
b110 &
0"
#430
0$
1"
#440
b1 '
0"
#450
b10 '
1"
#460
b11 '
0"
#470
b100 '
1"
#480
b101 '
0"
#490
1!
b0 '
1"
#500
b1 '
0"
#510
b10 '
1"
#520
b11 '
0"
#530
b100 '
1"
#540
b101 '
0"
#550
0!
b0 '
1"
#560
b1 '
0"
#570
b10 '
1"
#580
b11 '
0"
#590
b100 '
1"
#600
b101 '
0"
#610
1!
b0 '
1"
#620
b1 '
0"
#630
b10 '
1"
#640
b11 '
0"
#650
b100 '
1"
#660
b101 '
0"
#670
0!
b0 '
1"
#680
b1 '
0"
#690
b10 '
1"
#700
b11 '
0"
#710
b100 '
1"
#720
b101 '
0"
#730
1!
b0 '
1"
#740
b1 '
0"
#750
b10 '
1"
#760
b11 '
0"
#770
b100 '
1"
#780
b101 '
0"
#790
0!
b0 '
1"
#800
b111 #
b111 %
b1 '
0"
#810
1$
b10 '
1"
#820
b0 '
b111 &
0"
#830
0$
1"
#840
b1 '
0"
#850
b10 '
1"
#860
b11 '
0"
#870
b100 '
1"
#880
b101 '
0"
#890
b110 '
1"
#900
1!
b0 '
0"
#910
b1 '
1"
#920
b10 '
0"
#930
b11 '
1"
#940
b100 '
0"
#950
b101 '
1"
#960
b110 '
0"
#970
0!
b0 '
1"
#980
b1 '
0"
#990
b10 '
1"
#1000
b11 '
0"
#1010
b100 '
1"
#1020
b101 '
0"
#1030
b110 '
1"
#1040
1!
b0 '
0"
#1050
b1 '
1"
#1060
b10 '
0"
#1070
b11 '
1"
#1080
b100 '
0"
#1090
b101 '
1"
#1100
b110 '
0"
#1110
0!
b0 '
1"
#1120
b1 '
0"
#1130
b10 '
1"
#1140
b11 '
0"
#1150
b100 '
1"
#1160
b101 '
0"
#1170
b110 '
1"
#1180
1!
b0 '
0"
#1190
b1 '
1"
#1200
b10 '
0"
