Lab1/logarithm/logarithm.v
module logarithm (
    input wire [7:0] inVector,
    output reg [2:0] outNumber
);

    integer i;
    always @(inVector) begin
        outNumber = 0;
        for(i = 0; i < 7 && ~inVector[i]; i = i + 1) //подразумевается, что 1 когда нибудь встретится
            outNumber = i + 1;
    end
endmodule

Lab1/logarithm/test_module.v
module test_module;

    reg [2:0] inValue;
    wire [7:0] midVector;
    wire [2:0] outValue;

    //Если logarithm реализован правильно но inValue == outValue

    decoder decoder1(inValue, midVector);
    logarithm logarithm1(midVector, outValue);

    initial begin
        inValue = 4'b0;
    end

    always @(inValue)
        begin
            #5
            if(inValue  == outValue)
                $display("Success!");
            else
                $display("Jopa!",, inValue,, outValue);
        end

    always
        begin
            #10 inValue = inValue + 1;
        end

    initial
        $monitor(inValue,, midVector,, outValue);

    initial
        #300 $finish();

    initial begin
        $dumpfile("test.vcd");
        $dumpvars(0, test_module); //levels, top-module
    end

endmodule

module decoder(
    input wire [2:0] inNumber,
    output wire [7:0] outVector
);
    assign outVector = 8'b1 << inNumber;

endmodule

Lab1/logarithm/test.vcd
$date
	Wed May  3 21:50:35 2023
$end
$version
	Icarus Verilog
$end
$timescale
	1s
$end
$scope module test_module $end
$var wire 3 ! outValue [2:0] $end
$var wire 8 " midVector [7:0] $end
$var reg 3 # inValue [2:0] $end
$scope module decoder1 $end
$var wire 3 $ inNumber [2:0] $end
$var wire 8 % outVector [7:0] $end
$upscope $end
$scope module logarithm1 $end
$var wire 8 & inVector [7:0] $end
$var reg 3 ' outNumber [2:0] $end
$var integer 32 ( i [31:0] $end
$upscope $end
$upscope $end
$enddefinitions $end
#0
$dumpvars
b0 (
b0 '
b1 &
b1 %
b0 $
b0 #
b1 "
b0 !
$end
#10
b1 (
b1 !
b1 '
b10 "
b10 %
b10 &
b1 #
b1 $
#20
b10 (
b10 !
b10 '
b100 "
b100 %
b100 &
b10 #
b10 $
#30
b11 (
b11 !
b11 '
b1000 "
b1000 %
b1000 &
b11 #
b11 $
#40
b100 (
b100 !
b100 '
b10000 "
b10000 %
b10000 &
b100 #
b100 $
#50
b101 (
b101 !
b101 '
b100000 "
b100000 %
b100000 &
b101 #
b101 $
#60
b110 (
b110 !
b110 '
b1000000 "
b1000000 %
b1000000 &
b110 #
b110 $
#70
b111 (
b111 !
b111 '
b10000000 "
b10000000 %
b10000000 &
b111 #
b111 $
#80
b0 (
b0 !
b0 '
b1 "
b1 %
b1 &
b0 #
b0 $
#90
b1 (
b1 !
b1 '
b10 "
b10 %
b10 &
b1 #
b1 $
#100
b10 (
b10 !
b10 '
b100 "
b100 %
b100 &
b10 #
b10 $
#110
b11 (
b11 !
b11 '
b1000 "
b1000 %
b1000 &
b11 #
b11 $
#120
b100 (
b100 !
b100 '
b10000 "
b10000 %
b10000 &
b100 #
b100 $
#130
b101 (
b101 !
b101 '
b100000 "
b100000 %
b100000 &
b101 #
b101 $
#140
b110 (
b110 !
b110 '
b1000000 "
b1000000 %
b1000000 &
b110 #
b110 $
#150
b111 (
b111 !
b111 '
b10000000 "
b10000000 %
b10000000 &
b111 #
b111 $
#160
b0 (
b0 !
b0 '
b1 "
b1 %
b1 &
b0 #
b0 $
#170
b1 (
b1 !
b1 '
b10 "
b10 %
b10 &
b1 #
b1 $
#180
b10 (
b10 !
b10 '
b100 "
b100 %
b100 &
b10 #
b10 $
#190
b11 (
b11 !
b11 '
b1000 "
b1000 %
b1000 &
b11 #
b11 $
#200
b100 (
b100 !
b100 '
b10000 "
b10000 %
b10000 &
b100 #
b100 $
#210
b101 (
b101 !
b101 '
b100000 "
b100000 %
b100000 &
b101 #
b101 $
#220
b110 (
b110 !
b110 '
b1000000 "
b1000000 %
b1000000 &
b110 #
b110 $
#230
b111 (
b111 !
b111 '
b10000000 "
b10000000 %
b10000000 &
b111 #
b111 $
#240
b0 (
b0 !
b0 '
b1 "
b1 %
b1 &
b0 #
b0 $
#250
b1 (
b1 !
b1 '
b10 "
b10 %
b10 &
b1 #
b1 $
#260
b10 (
b10 !
b10 '
b100 "
b100 %
b100 &
b10 #
b10 $
#270
b11 (
b11 !
b11 '
b1000 "
b1000 %
b1000 &
b11 #
b11 $
#280
b100 (
b100 !
b100 '
b10000 "
b10000 %
b10000 &
b100 #
b100 $
#290
b101 (
b101 !
b101 '
b100000 "
b100000 %
b100000 &
b101 #
b101 $
#300
b110 (
b110 !
b110 '
b1000000 "
b1000000 %
b1000000 &
b110 #
b110 $
