Lab2/homework/Pulse-generator/pulse_gen.v
module pulse_gen#(
    parameter BIN_SIZE = 8
)(
    input wire rst,
    input wire clk,
    input wire [7:0] countInByTwo, // на вход частота в два раза меньше требуемой
    output wire out
);

    reg [BIN_SIZE - 1:0] num; // эт кол-во отсчитанных тактов
    reg [BIN_SIZE - 1:0] countByTwo;
    assign out = (num == 0) ? 1 : 0;

    always @(posedge clk) begin
        if(rst) begin
            countByTwo <= countInByTwo;
            num <= 0;
        end
        else begin
            if(num + 1 == countByTwo) begin
                num <= 0;
            end
            else
                num <= num + 1;
        end


    end

endmodule

Lab2/homework/Pulse-generator/test.v
`include "pulse_gen.v"

module test;
    //construction of test module
    reg clk;
    initial begin
        clk <= 0;
    end

    reg reset;
    initial begin
        reset <= 0;
        @(posedge clk);
        reset <= 1;
        @(posedge clk);
        reset <= 0;

        repeat(2) begin
            #380
            reset <= 0;
            @(posedge clk);
            reset <= 1;
            @(posedge clk);
            reset <= 0;
        end
    end

    reg [7:0] countIn;
    initial begin
        countIn <= 8'd2;
        #400 countIn <= 8'd3;
        #400 countIn <= 8'd4;
    end

    always begin
        #10 clk <= ~clk;
    end

    //module itself
    wire out;
    pulse_gen pulse_gen1(reset, clk, countIn, out);

    //dump settings
    initial begin
        $monitor(reset,, clk,, countIn,, out);
    end

    initial begin
        $dumpfile("test.vcd");
        $dumpvars(1, test, pulse_gen1);
    end

    initial begin
        #1200 $finish();
    end

endmodule

Lab2/homework/Pulse-generator/test.vcd
$date
	Mon May  8 15:02:15 2023
$end
$version
	Icarus Verilog
$end
$timescale
	1s
$end
$scope module test $end
$var wire 1 ! out $end
$var reg 1 " clk $end
$var reg 8 # countIn [7:0] $end
$var reg 1 $ reset $end
$upscope $end
$scope module test $end
$scope module pulse_gen1 $end
$var wire 1 " clk $end
$var wire 8 % countInByTwo [7:0] $end
$var wire 1 $ rst $end
$var wire 1 ! out $end
$var reg 8 & countByTwo [7:0] $end
$var reg 8 ' num [7:0] $end
$upscope $end
$upscope $end
$enddefinitions $end
#0
$dumpvars
bx '
bx &
b10 %
0$
b10 #
0"
x!
$end
#10
1$
1"
#20
0"
#30
1!
0$
b0 '
b10 &
1"
#40
0"
#50
0!
b1 '
1"
#60
0"
#70
1!
b0 '
1"
#80
0"
#90
0!
b1 '
1"
#100
0"
#110
1!
b0 '
1"
#120
0"
#130
0!
b1 '
1"
#140
0"
#150
1!
b0 '
1"
#160
0"
#170
0!
b1 '
1"
#180
0"
#190
1!
b0 '
1"
#200
0"
#210
0!
b1 '
1"
#220
0"
#230
1!
b0 '
1"
#240
0"
#250
0!
b1 '
1"
#260
0"
#270
1!
b0 '
1"
#280
0"
#290
0!
b1 '
1"
#300
0"
#310
1!
b0 '
1"
#320
0"
#330
0!
b1 '
1"
#340
0"
#350
1!
b0 '
1"
#360
0"
#370
0!
b1 '
1"
#380
0"
#390
1!
b0 '
1"
#400
0"
b11 #
b11 %
#410
0!
b1 '
1$
1"
#420
0"
#430
1!
0$
b0 '
b11 &
1"
#440
0"
#450
0!
b1 '
1"
#460
0"
#470
b10 '
1"
#480
0"
#490
1!
b0 '
1"
#500
0"
#510
0!
b1 '
1"
#520
0"
#530
b10 '
1"
#540
0"
#550
1!
b0 '
1"
#560
0"
#570
0!
b1 '
1"
#580
0"
#590
b10 '
1"
#600
0"
#610
1!
b0 '
1"
#620
0"
#630
0!
b1 '
1"
#640
0"
#650
b10 '
1"
#660
0"
#670
1!
b0 '
1"
#680
0"
#690
0!
b1 '
1"
#700
0"
#710
b10 '
1"
#720
0"
#730
1!
b0 '
1"
#740
0"
#750
0!
b1 '
1"
#760
0"
#770
b10 '
1"
#780
0"
#790
1!
b0 '
1"
#800
0"
b100 #
b100 %
#810
0!
b1 '
1$
1"
#820
0"
#830
1!
0$
b0 '
b100 &
1"
#840
0"
#850
0!
b1 '
1"
#860
0"
#870
b10 '
1"
#880
0"
#890
b11 '
1"
#900
0"
#910
1!
b0 '
1"
#920
0"
#930
0!
b1 '
1"
#940
0"
#950
b10 '
1"
#960
0"
#970
b11 '
1"
#980
0"
#990
1!
b0 '
1"
#1000
0"
#1010
0!
b1 '
1"
#1020
0"
#1030
b10 '
1"
#1040
0"
#1050
b11 '
1"
#1060
0"
#1070
1!
b0 '
1"
#1080
0"
#1090
0!
b1 '
1"
#1100
0"
#1110
b10 '
1"
#1120
0"
#1130
b11 '
1"
#1140
0"
#1150
1!
b0 '
1"
#1160
0"
#1170
0!
b1 '
1"
#1180
0"
#1190
b10 '
1"
