Lab2/homework/Pulse-generator/pulse_gen.v
module pulse_gen(

    input wire rst,
    input wire clk,
    input wire [7:0] countIn,
    output wire out
);

    reg [7:0] num;  //я не придумал как его назвать лучше... // эт кол-во отсчитанных тактов
    reg [7:0] count;
    assign out = (num == 0) ? 1 : 0;

    always @(clk) begin
        if(rst) begin
            count = countIn;
            num = 0;
        end
        else begin
            num = num + 1;
        end

        if(num == count) begin
            num = 0;
        end
    end

endmodule

Lab2/homework/Pulse-generator/test.v
`include "pulse_gen.v"

module test;
    //construction of test module
    reg clk;
    initial begin
        clk <= 0;
    end

    reg reset;
    initial begin
        reset <= 0;
        @(posedge clk);
        reset <= 1;
        @(posedge clk);
        reset <= 0;

        repeat(2) begin
            #380
            reset <= 0;
            @(posedge clk);
            reset <= 1;
            @(posedge clk);
            reset <= 0;
        end
    end

    reg [7:0] countIn;
    initial begin
        countIn <= 8'd5;
        #400 countIn <= 8'd6;
        #400 countIn <= 8'd7;
    end

    always begin
        #10 clk = ~clk;
    end

    //module itself
    wire out;
    pulse_gen pulse_gen1(reset, clk, countIn, out);

    //dump settings
    initial begin
        $monitor(reset,, clk,, countIn,, out);
    end

    initial begin
        $dumpfile("test.vcd");
        $dumpvars(1, test, pulse_gen1);
    end

    initial begin
        #1200 $finish();
    end

endmodule

Lab2/homework/Pulse-generator/test.vcd
$date
	Sun May  7 00:25:22 2023
$end
$version
	Icarus Verilog
$end
$timescale
	1s
$end
$scope module test $end
$var wire 1 ! out $end
$var reg 1 " clk $end
$var reg 8 # countIn [7:0] $end
$var reg 1 $ reset $end
$upscope $end
$scope module test $end
$scope module pulse_gen1 $end
$var wire 1 " clk $end
$var wire 8 % countIn [7:0] $end
$var wire 1 $ rst $end
$var wire 1 ! out $end
$var reg 8 & count [7:0] $end
$var reg 8 ' num [7:0] $end
$upscope $end
$upscope $end
$enddefinitions $end
#0
$dumpvars
bx '
bx &
b101 %
0$
b101 #
0"
x!
$end
#10
1$
1"
#20
1!
b0 '
b101 &
0"
#30
0$
1"
#40
0!
b1 '
0"
#50
b10 '
1"
#60
b11 '
0"
#70
b100 '
1"
#80
1!
b0 '
0"
#90
0!
b1 '
1"
#100
b10 '
0"
#110
b11 '
1"
#120
b100 '
0"
#130
1!
b0 '
1"
#140
0!
b1 '
0"
#150
b10 '
1"
#160
b11 '
0"
#170
b100 '
1"
#180
1!
b0 '
0"
#190
0!
b1 '
1"
#200
b10 '
0"
#210
b11 '
1"
#220
b100 '
0"
#230
1!
b0 '
1"
#240
0!
b1 '
0"
#250
b10 '
1"
#260
b11 '
0"
#270
b100 '
1"
#280
1!
b0 '
0"
#290
0!
b1 '
1"
#300
b10 '
0"
#310
b11 '
1"
#320
b100 '
0"
#330
1!
b0 '
1"
#340
0!
b1 '
0"
#350
b10 '
1"
#360
b11 '
0"
#370
b100 '
1"
#380
1!
b0 '
0"
#390
0!
b1 '
1"
#400
b110 #
b110 %
b10 '
0"
#410
1$
b11 '
1"
#420
1!
b0 '
b110 &
0"
#430
0$
1"
#440
0!
b1 '
0"
#450
b10 '
1"
#460
b11 '
0"
#470
b100 '
1"
#480
b101 '
0"
#490
1!
b0 '
1"
#500
0!
b1 '
0"
#510
b10 '
1"
#520
b11 '
0"
#530
b100 '
1"
#540
b101 '
0"
#550
1!
b0 '
1"
#560
0!
b1 '
0"
#570
b10 '
1"
#580
b11 '
0"
#590
b100 '
1"
#600
b101 '
0"
#610
1!
b0 '
1"
#620
0!
b1 '
0"
#630
b10 '
1"
#640
b11 '
0"
#650
b100 '
1"
#660
b101 '
0"
#670
1!
b0 '
1"
#680
0!
b1 '
0"
#690
b10 '
1"
#700
b11 '
0"
#710
b100 '
1"
#720
b101 '
0"
#730
1!
b0 '
1"
#740
0!
b1 '
0"
#750
b10 '
1"
#760
b11 '
0"
#770
b100 '
1"
#780
b101 '
0"
#790
1!
b0 '
1"
#800
b111 #
b111 %
0!
b1 '
0"
#810
1$
b10 '
1"
#820
1!
b0 '
b111 &
0"
#830
0$
1"
#840
0!
b1 '
0"
#850
b10 '
1"
#860
b11 '
0"
#870
b100 '
1"
#880
b101 '
0"
#890
b110 '
1"
#900
1!
b0 '
0"
#910
0!
b1 '
1"
#920
b10 '
0"
#930
b11 '
1"
#940
b100 '
0"
#950
b101 '
1"
#960
b110 '
0"
#970
1!
b0 '
1"
#980
0!
b1 '
0"
#990
b10 '
1"
#1000
b11 '
0"
#1010
b100 '
1"
#1020
b101 '
0"
#1030
b110 '
1"
#1040
1!
b0 '
0"
#1050
0!
b1 '
1"
#1060
b10 '
0"
#1070
b11 '
1"
#1080
b100 '
0"
#1090
b101 '
1"
#1100
b110 '
0"
#1110
1!
b0 '
1"
#1120
0!
b1 '
0"
#1130
b10 '
1"
#1140
b11 '
0"
#1150
b100 '
1"
#1160
b101 '
0"
#1170
b110 '
1"
#1180
1!
b0 '
0"
#1190
0!
b1 '
1"
#1200
b10 '
0"
