Lab4/filo.v
module filo #(
    parameter FIFO_DEPTH = 8,
    parameter DATA_WIDTH = 8
)(
    input wire clk,
    input wire reset,
    input wire rd_en,
    input wire wr_en,
    input wire [DATA_WIDTH - 1 : 0] wr_data,
    output reg [DATA_WIDTH - 1 : 0] rd_data,
    output wire wr_ready,
    output reg rd_val
);
    reg [DATA_WIDTH - 1 : 0] array [FIFO_DEPTH - 1 : 0];
    reg [$clog2(FIFO_DEPTH + 1) - 1 : 0] len;

    assign wr_ready = !(len == FIFO_DEPTH);

    always @(posedge clk) begin
        if(rd_en)
            rd_data <= array[0];
    end

    generate if(FIFO_DEPTH > 1) begin : ifgenStack
        always @(posedge clk) begin
            if(wr_en) begin
                array[0] <= wr_data;
            end
            else if(reset) begin
                array[0] <= 0;
            end
            else if(rd_en) begin
                array[0] <= array[1];
            end
        end
    end
    else if(FIFO_DEPTH == 1) begin : ifgenSimpleStack
        always  @(posedge clk) begin
            if(wr_en) begin
                array[0] <= wr_data;
            end
            else if(reset) begin
                array[0] <= 0;
            end
        end
    end
    endgenerate

    genvar i;
    generate for(i = 1; i < FIFO_DEPTH; i = i + 1) begin : loopArray
        if(i != FIFO_DEPTH - 1) begin
            always @(posedge clk)
                if(reset)
                    array[i] <= 0;
                else if(wr_en && !rd_en)
                    array[i] <= array[i - 1];
                else if(!wr_en && rd_en)
                    array[i] <= array[i + 1];
        end
        else begin
            always @(posedge clk)
                if(reset)
                    array[i] <= 0;
                else if(wr_en && !rd_en)
                    array[i] <= array[i - 1];
        end
    end
    endgenerate

    always @(posedge clk) begin
        if(rd_en)
            rd_val <= !(len == 0);
    end

    always  @(posedge clk) begin
        if(reset) begin
            if(wr_en)
                len <= 1;
            else
                len <= 0;
        end
        else if(!wr_en && rd_en && len > 0)
            len <= len - 1;
        else if(wr_en && !rd_en && len < FIFO_DEPTH)
            len <= len + 1;
        else if(wr_en && rd_en && len == 0)
            len <= 1;
    end
endmodule

Lab4/fifo.v
module fifo #(
    parameter FIFO_DEPTH = 8,
    parameter DATA_WIDTH = 8
)(
    input wire clk,
    input wire reset,
    input wire rd_en,
    input wire wr_en,
    input wire [DATA_WIDTH - 1 : 0] wr_data,
    output reg [DATA_WIDTH - 1 : 0] rd_data,
    output wire wr_ready,
    output reg rd_val
);
    reg [DATA_WIDTH - 1 : 0] array [FIFO_DEPTH - 1 : 0];
    reg [$clog2(FIFO_DEPTH) : 0] len;

    assign wr_ready = !(len == FIFO_DEPTH);

    //вынес за знаки условий общие действия
    always @(posedge clk) begin
        if(wr_en) begin
            array[0] <= wr_data;
        end
        if(rd_en) begin
            rd_data <= array[0];
            rd_val <= !(len == 0);
        end
    end

    //далее пошли различия по алгоритму действий
    //RESET
    always @(posedge clk) begin
        if(reset) begin
            if(wr_en) begin
                len <= 1;
            end
            else begin
                array[0] <= 0;
                len <= 0;
            end
        end
    end

    genvar i;
    generate for(i = 1; i < FIFO_DEPTH; i = i + 1)
        always @(posedge clk)
            if(reset)
                array[i] <= 0;
    endgenerate

    //READ
    wire onlyRD;
    assign onlyRD = !reset && !wr_en && rd_en;

    always @(posedge clk) begin
        if(onlyRD && len > 0)
                len <= len - 1;
    end

    generate for(i = 0; i < FIFO_DEPTH - 1; i = i + 1)
        always @(posedge clk)
            if(onlyRD)
                array[i] <= array[i + 1];
    endgenerate

    //WRITE
    wire onlyWR;
    assign onlyWR = !reset && !rd_en && wr_en;

    always @(posedge clk) begin
        if(onlyWR && len < FIFO_DEPTH) //типа первый элемент загружен
                len <= len + 1;
    end

    generate for(i = 0; i < FIFO_DEPTH - 1; i = i + 1)
        always @(posedge clk)
            if(onlyWR)
                array[i + 1] <= array[i];
    endgenerate

    //READ&WRITE
    wire onlyRDWR;
    assign onlyRDWR = !reset && rd_en && wr_en;

    always @(posedge clk)
        if(onlyRDWR && len == 0)
            len <= 1;
endmodule
//наверное я фигово оформил, пока чето красивое пытаюсь выдавать

Lab4/test.v
`include "filo.v"
module test;

    reg clk = 1;
    always #5 clk = ~clk;

    reg reset;
    reg rd_en;
    reg wr_en;
    reg [7 : 0] wr_data;
    wire [7 : 0] rd_data;
    wire wr_ready;
    wire rd_val;


    fifo fifo1(clk, reset, rd_en, wr_en, wr_data, rd_data, wr_ready, rd_val);

    integer i;
    initial begin
        reset <= 1;
        wr_en <= 0;
        rd_en <= 0;
        #10 reset <= 0;
        wr_en <= 1;
        for(i = 8; i >= 0; i = i - 1) begin
            wr_data <= i;
            #10;
        end
        wr_en <= 0;
        rd_en <= 1;
        for(i = 0; i < 9; i = i + 1) begin
            #10;
        end
        #10 rd_en <= 0;

        #100;
        wr_en <= 1;
        rd_en <= 1;
        for(i = 8; i >= 0; i = i - 1) begin
            wr_data <= i;
            #10;
        end
        wr_en <= 0;
        rd_en <= 0;

        #100;
        wr_en <= 1;
        rd_en <= 1;
        reset <= 1;
        wr_data = 8'b00000010;
        #10;
        wr_en <= 0;
        reset <= 0;
        #10 rd_en <= 0;
    end
    //dump settings
    initial begin
        $monitor(rd_data, " ", rd_val);
    end

    initial begin
        $dumpfile("test.vcd");
        $dumpvars(2, test);
    end

    initial begin
        #2000 $finish();
    end

endmodule

Lab4/test.vcd
$date
	Tue Jul  4 09:47:23 2023
$end
$version
	Icarus Verilog
$end
$timescale
	1s
$end
$scope module test $end
$var wire 1 ! wr_ready $end
$var wire 1 " rd_val $end
$var wire 8 # rd_data [7:0] $end
$var reg 1 $ clk $end
$var reg 1 % rd_en $end
$var reg 1 & reset $end
$var reg 8 ' wr_data [7:0] $end
$var reg 1 ( wr_en $end
$var integer 32 ) i [31:0] $end
$scope module fifo1 $end
$var wire 1 $ clk $end
$var wire 1 * onlyRD $end
$var wire 1 + onlyRDWR $end
$var wire 1 , onlyWR $end
$var wire 1 % rd_en $end
$var wire 1 & reset $end
$var wire 8 - wr_data [7:0] $end
$var wire 1 ( wr_en $end
$var wire 1 ! wr_ready $end
$var reg 4 . len [3:0] $end
$var reg 8 / rd_data [7:0] $end
$var reg 1 " rd_val $end
$upscope $end
$upscope $end
$enddefinitions $end
#0
$dumpvars
bx /
bx .
bx -
0,
0+
0*
bx )
0(
bx '
1&
0%
1$
bx #
x"
x!
$end
#5
0$
#10
1,
1!
b0 .
b1000 '
b1000 -
1(
0&
1$
b1000 )
#15
0$
#20
b1 .
b111 '
b111 -
1$
b111 )
#25
0$
#30
b10 .
b110 '
b110 -
1$
b110 )
#35
0$
#40
b11 .
b101 '
b101 -
1$
b101 )
#45
0$
#50
b100 .
b100 '
b100 -
1$
b100 )
#55
0$
#60
b101 .
b11 '
b11 -
1$
b11 )
#65
0$
#70
b110 .
b10 '
b10 -
1$
b10 )
#75
0$
#80
b111 .
b1 '
b1 -
1$
b1 )
#85
0$
#90
0!
b1000 .
b0 '
b0 -
1$
b0 )
#95
0$
#100
1*
0,
1%
0(
1$
b0 )
#105
0$
#110
1!
b111 .
1"
b0 #
b0 /
1$
b1 )
#115
0$
#120
b1 #
b1 /
b110 .
1$
b10 )
#125
0$
#130
b101 .
b10 #
b10 /
1$
b11 )
#135
0$
#140
b11 #
b11 /
b100 .
1$
b100 )
#145
0$
#150
b11 .
b100 #
b100 /
1$
b101 )
#155
0$
#160
b101 #
b101 /
b10 .
1$
b110 )
#165
0$
#170
b1 .
b110 #
b110 /
1$
b111 )
#175
0$
#180
b111 #
b111 /
b0 .
1$
b1000 )
#185
0$
#190
0"
1$
b1001 )
#195
0$
#200
0*
0%
1$
#205
0$
#210
1$
#215
0$
#220
1$
#225
0$
#230
1$
#235
0$
#240
1$
#245
0$
#250
1$
#255
0$
#260
1$
#265
0$
#270
1$
#275
0$
#280
1$
#285
0$
#290
1$
#295
0$
#300
1+
0,
b1000 '
b1000 -
1%
1(
1$
b1000 )
#305
0$
#310
b1 .
b111 '
b111 -
1$
b111 )
#315
0$
#320
1"
b1000 #
b1000 /
b110 '
b110 -
1$
b110 )
#325
0$
#330
b111 #
b111 /
b101 '
b101 -
1$
b101 )
#335
0$
#340
b110 #
b110 /
b100 '
b100 -
1$
b100 )
#345
0$
#350
b101 #
b101 /
b11 '
b11 -
1$
b11 )
#355
0$
#360
b100 #
b100 /
b10 '
b10 -
1$
b10 )
#365
0$
#370
b11 #
b11 /
b1 '
b1 -
1$
b1 )
#375
0$
#380
b10 #
b10 /
b0 '
b0 -
1$
b0 )
#385
0$
#390
0+
b1 #
b1 /
0%
0(
1$
b11111111111111111111111111111111 )
#395
0$
#400
1$
#405
0$
#410
1$
#415
0$
#420
1$
#425
0$
#430
1$
#435
0$
#440
1$
#445
0$
#450
1$
#455
0$
#460
1$
#465
0$
#470
1$
#475
0$
#480
1$
#485
0$
#490
0,
1&
1%
1(
1$
b10 '
b10 -
#495
0$
#500
1*
b0 #
b0 /
0&
0(
1$
#505
0$
#510
0*
b0 .
b10 #
b10 /
0%
1$
