Lab5/fifo_shift.v
module fifo_shift #(
    parameter FIFO_DEPTH = 8,
    parameter DATA_WIDTH = 8
)(
    input wire clk,
    input wire reset,
    input wire rd_en,
    input wire wr_en,
    input wire [DATA_WIDTH - 1 : 0] wr_data,
    output wire [DATA_WIDTH - 1 : 0] rd_data,
    output wire wr_ready,
    output wire rd_ready,
    output reg rd_val
);
    localparam LEN_LENTH = $clog2(FIFO_DEPTH + 1); //лен лен

    reg [DATA_WIDTH - 1 : 0] array [FIFO_DEPTH - 1 : 0];
    reg [LEN_LENTH - 1 : 0] len;

    assign wr_ready = len < FIFO_DEPTH;
    assign rd_ready = len > 0;

    assign rd_data = array[len - rd_ready];

    always @(posedge clk) begin
        if(reset)
            rd_val <= 0;
        else
            rd_val <= (rd_en) ? rd_ready : rd_val;
    end


    genvar i;
    generate for(i = 0; i < FIFO_DEPTH; i = i + 1) begin : loopArray
        if(i == 0) begin
            always @(posedge clk) begin
                if(reset)
                    array[i] <= array[i];
                else
                    array[i] <= (wr_en & wr_ready) ? wr_data : array[0];
            end
        end
        else begin
            always @(posedge clk) begin
                if(reset)
                    array[i] <= array[i];
                else
                    array[i] <= (wr_en & wr_ready) ? array[i - 1] : array[i];
            end
        end
    end
    endgenerate

    always  @(posedge clk) begin
        if(reset)
            len <= 0;
        else
            len <= (~wr_en & rd_en & len > 0) ? len - 1 :
                (wr_en & ~rd_en & wr_ready) ? len + 1 :
                (wr_en & rd_en & len == 0) ? 1 : len;
    end
endmodule

Lab5/test.v
`include "fifo_shift.v"
module test;

    reg clk = 1;
    always #5 clk = ~clk;

    reg reset;
    reg rd_en;
    reg wr_en;
    reg [7 : 0] wr_data;
    wire [7 : 0] rd_data;
    wire wr_ready;
    wire rd_ready;
    wire rd_val;


    fifo_shift fifo1(clk, reset, rd_en, wr_en, wr_data, rd_data, wr_ready, rd_ready, rd_val);

    integer i;
    initial begin
        reset <= 1;
        wr_en <= 0;
        rd_en <= 0;
        #10 reset <= 0;
        wr_en <= 1;
        for(i = 8; i >= 0; i = i - 1) begin
            wr_data <= i;
            #10;
        end
        wr_en <= 0;
        rd_en <= 1;
        for(i = 0; i < 9; i = i + 1) begin
            #10;
        end
        #10 rd_en <= 0;

        #100;
        wr_en <= 1;
        rd_en <= 1;
        for(i = 9; i >= 1; i = i - 1) begin
            wr_data <= i;
            #10;
        end
        wr_en <= 0;
        rd_en <= 0;

        #100; //кусок от другого теста
        wr_en <= 1;
        rd_en <= 1;
        reset <= 1;
        wr_data = 8'b00000010;
        #10;
        wr_en <= 0;
        reset <= 0;
        #10 rd_en <= 0;
    end
    //dump settings
    initial begin
        $monitor(rd_data, " ", rd_val);
    end

    initial begin
        $dumpfile("test.vcd");
        $dumpvars(2, test);
    end

    initial begin
        #2000 $finish();
    end

endmodule

Lab5/test.vcd
$date
	Fri Jul 14 09:22:32 2023
$end
$version
	Icarus Verilog
$end
$timescale
	1s
$end
$scope module test $end
$var wire 1 ! wr_ready $end
$var wire 1 " rd_val $end
$var wire 1 # rd_ready $end
$var wire 8 $ rd_data [7:0] $end
$var reg 1 % clk $end
$var reg 1 & rd_en $end
$var reg 1 ' reset $end
$var reg 8 ( wr_data [7:0] $end
$var reg 1 ) wr_en $end
$var integer 32 * i [31:0] $end
$scope module fifo1 $end
$var wire 1 % clk $end
$var wire 8 + rd_data [7:0] $end
$var wire 1 & rd_en $end
$var wire 1 ' reset $end
$var wire 8 , wr_data [7:0] $end
$var wire 1 ) wr_en $end
$var wire 1 ! wr_ready $end
$var wire 1 # rd_ready $end
$var reg 4 - len [3:0] $end
$var reg 1 " rd_val $end
$upscope $end
$upscope $end
$enddefinitions $end
#0
$dumpvars
bx -
bx ,
bx +
bx *
0)
bx (
1'
0&
1%
bx $
x#
x"
x!
$end
#5
0%
#10
1!
0#
b0 -
0"
b1000 (
b1000 ,
1)
0'
1%
b1000 *
#15
0%
#20
b1000 $
b1000 +
1#
b1 -
b111 (
b111 ,
1%
b111 *
#25
0%
#30
b10 -
b1000 $
b1000 +
b110 (
b110 ,
1%
b110 *
#35
0%
#40
b1000 $
b1000 +
b11 -
b101 (
b101 ,
1%
b101 *
#45
0%
#50
b100 -
b1000 $
b1000 +
b100 (
b100 ,
1%
b100 *
#55
0%
#60
b1000 $
b1000 +
b101 -
b11 (
b11 ,
1%
b11 *
#65
0%
#70
b110 -
b1000 $
b1000 +
b10 (
b10 ,
1%
b10 *
#75
0%
#80
b1000 $
b1000 +
b111 -
b1 (
b1 ,
1%
b1 *
#85
0%
#90
0!
b1000 -
b1000 $
b1000 +
b0 (
b0 ,
1%
b0 *
#95
0%
#100
1&
0)
1%
b0 *
#105
0%
#110
1!
b111 $
b111 +
b111 -
1"
1%
b1 *
#115
0%
#120
b110 $
b110 +
b110 -
1%
b10 *
#125
0%
#130
b101 $
b101 +
b101 -
1%
b11 *
#135
0%
#140
b100 $
b100 +
b100 -
1%
b100 *
#145
0%
#150
b11 $
b11 +
b11 -
1%
b101 *
#155
0%
#160
b10 $
b10 +
b10 -
1%
b110 *
#165
0%
#170
b1 $
b1 +
b1 -
1%
b111 *
#175
0%
#180
0#
b1 $
b1 +
b0 -
1%
b1000 *
#185
0%
#190
0"
1%
b1001 *
#195
0%
#200
0&
1%
#205
0%
#210
1%
#215
0%
#220
1%
#225
0%
#230
1%
#235
0%
#240
1%
#245
0%
#250
1%
#255
0%
#260
1%
#265
0%
#270
1%
#275
0%
#280
1%
#285
0%
#290
1%
#295
0%
#300
b1001 (
b1001 ,
1&
1)
1%
#305
0%
#310
1#
b1 -
b1001 $
b1001 +
b1000 (
b1000 ,
1%
b1000 *
#315
0%
#320
b1000 $
b1000 +
1"
b111 (
b111 ,
1%
b111 *
#325
0%
#330
b111 $
b111 +
b110 (
b110 ,
1%
b110 *
#335
0%
#340
b110 $
b110 +
b101 (
b101 ,
1%
b101 *
#345
0%
#350
b101 $
b101 +
b100 (
b100 ,
1%
b100 *
#355
0%
#360
b100 $
b100 +
b11 (
b11 ,
1%
b11 *
#365
0%
#370
b11 $
b11 +
b10 (
b10 ,
1%
b10 *
#375
0%
#380
b10 $
b10 +
b1 (
b1 ,
1%
b1 *
#385
0%
#390
b1 $
b1 +
0&
0)
1%
b0 *
#395
0%
#400
1%
#405
0%
#410
1%
#415
0%
#420
1%
#425
0%
#430
1%
#435
0%
#440
1%
#445
0%
#450
1%
#455
0%
#460
1%
#465
0%
#470
1%
#475
0%
#480
1%
#485
0%
#490
1'
1&
1)
1%
b10 (
b10 ,
#495
0%
#500
0"
0#
b1 $
b1 +
b0 -
0'
0)
1%
#505
0%
#510
0&
1%
