Lab3/memory_module.v
module memory_module #(
    parameter DATA_WIDTH = 8,
    parameter MAX_ADDR = 64,
    parameter ADDRSIZE = log2(MAX_ADDR)
)(
    input wire clk,
    input wire rd_en,
    input wire [ADDRSIZE - 1 : 0] rd_addr,
    input wire wr_en,
    input wire [ADDRSIZE - 1 : 0] wr_addr,
    input wire [DATA_WIDTH - 1 : 0] wr_data,
    output reg [DATA_WIDTH - 1 : 0] rd_data
);

    function integer log2; //тэээк как бы накалякать чтобы оно запустилось...
        input integer value;
        integer tmp;
        begin
            log2 = 0;
            for(tmp = 1; tmp < value; tmp = tmp * 2)
                log2 = log2 + 1;
        end
    endfunction

    reg [DATA_WIDTH - 1 : 0] mem_cell [MAX_ADDR - 1 : 0];
    reg rd_flag;
    reg [ADDRSIZE - 1 : 0] rd_last_addr;
    reg [DATA_WIDTH - 1 : 0] rd_last_value;

    always @(posedge clk) begin
        if(rd_flag) begin
            rd_data <= rd_last_value;
        end
        else if(!rd_en) begin
            rd_data <= 0;
        end

        if(rd_en) begin
            rd_last_value <= mem_cell[rd_addr];
            rd_flag <= 1;
        end
        else begin
            rd_flag <= 0;
        end

        if(wr_en) begin
            mem_cell[wr_addr] <= wr_data;
        end
    end


endmodule

Lab3/test.v
`include "memory_module.v"

module test;

    reg clk = 0;
    always #5 clk = ~clk;

    reg rd_en = 0;
    reg [5 : 0] rd_addr;
    reg wr_en = 0;
    reg [5 : 0] wr_addr;
    reg [7 : 0] wr_data;
    wire [7 : 0] rd_data;

    memory_module mem1(clk, rd_en, rd_addr, wr_en, wr_addr, wr_data, rd_data);

    integer i;
    initial begin
        wr_en <= 1;
        for(i = 0; i < 64; i = i + 1) begin
            #10 wr_addr <= i;
            wr_data <= i;
        end
        wr_en <= 0; //значение на 0x3F не запишется! да и фиг с ним, посмотрю чо будет
        rd_en <= 1;
        for(i = 0; i < 64; i = i + 1) begin
            rd_addr <= i;
            #10;
        end
        #10
        rd_en <= 0;
    end

    /*initial begin
        wr_en <= 1;
        wr_addr <= 0;
        wr_data <= 0;
        #10
        rd_addr <= 0;
        rd_en <= 1;
        wr_data <= 1;
    end
*/

    //dump settings
    initial begin
        $monitor(rd_data);
    end

    initial begin
        $dumpfile("test.vcd");
        $dumpvars(0, test);
    end

    initial begin
        #2000 $finish();
    end

endmodule

Lab3/test.vcd
$date
	Fri May 12 21:40:45 2023
$end
$version
	Icarus Verilog
$end
$timescale
	1s
$end
$scope module test $end
$var wire 8 ! rd_data [7:0] $end
$var reg 1 " clk $end
$var reg 6 # rd_addr [5:0] $end
$var reg 1 $ rd_en $end
$var reg 6 % wr_addr [5:0] $end
$var reg 8 & wr_data [7:0] $end
$var reg 1 ' wr_en $end
$var integer 32 ( i [31:0] $end
$scope module mem1 $end
$var wire 1 " clk $end
$var wire 6 ) rd_addr [5:0] $end
$var wire 1 $ rd_en $end
$var wire 6 * wr_addr [5:0] $end
$var wire 8 + wr_data [7:0] $end
$var wire 1 ' wr_en $end
$var reg 8 , rd_data [7:0] $end
$var reg 1 - rd_flag $end
$var reg 8 . rd_last_value [7:0] $end
$scope function log2 $end
$var integer 32 / tmp [31:0] $end
$var integer 32 0 value [31:0] $end
$upscope $end
$upscope $end
$upscope $end
$enddefinitions $end
#0
$dumpvars
bx 0
bx /
bx .
x-
bx ,
bx +
bx *
bx )
b0 (
1'
bx &
bx %
0$
bx #
0"
bx !
$end
#5
0-
b0 !
b0 ,
1"
#10
b0 &
b0 +
b0 %
b0 *
0"
b1 (
#15
1"
#20
b1 &
b1 +
b1 %
b1 *
0"
b10 (
#25
1"
#30
b10 &
b10 +
b10 %
b10 *
0"
b11 (
#35
1"
#40
b11 &
b11 +
b11 %
b11 *
0"
b100 (
#45
1"
#50
b100 &
b100 +
b100 %
b100 *
0"
b101 (
#55
1"
#60
b101 &
b101 +
b101 %
b101 *
0"
b110 (
#65
1"
#70
b110 &
b110 +
b110 %
b110 *
0"
b111 (
#75
1"
#80
b111 &
b111 +
b111 %
b111 *
0"
b1000 (
#85
1"
#90
b1000 &
b1000 +
b1000 %
b1000 *
0"
b1001 (
#95
1"
#100
b1001 &
b1001 +
b1001 %
b1001 *
0"
b1010 (
#105
1"
#110
b1010 &
b1010 +
b1010 %
b1010 *
0"
b1011 (
#115
1"
#120
b1011 &
b1011 +
b1011 %
b1011 *
0"
b1100 (
#125
1"
#130
b1100 &
b1100 +
b1100 %
b1100 *
0"
b1101 (
#135
1"
#140
b1101 &
b1101 +
b1101 %
b1101 *
0"
b1110 (
#145
1"
#150
b1110 &
b1110 +
b1110 %
b1110 *
0"
b1111 (
#155
1"
#160
b1111 &
b1111 +
b1111 %
b1111 *
0"
b10000 (
#165
1"
#170
b10000 &
b10000 +
b10000 %
b10000 *
0"
b10001 (
#175
1"
#180
b10001 &
b10001 +
b10001 %
b10001 *
0"
b10010 (
#185
1"
#190
b10010 &
b10010 +
b10010 %
b10010 *
0"
b10011 (
#195
1"
#200
b10011 &
b10011 +
b10011 %
b10011 *
0"
b10100 (
#205
1"
#210
b10100 &
b10100 +
b10100 %
b10100 *
0"
b10101 (
#215
1"
#220
b10101 &
b10101 +
b10101 %
b10101 *
0"
b10110 (
#225
1"
#230
b10110 &
b10110 +
b10110 %
b10110 *
0"
b10111 (
#235
1"
#240
b10111 &
b10111 +
b10111 %
b10111 *
0"
b11000 (
#245
1"
#250
b11000 &
b11000 +
b11000 %
b11000 *
0"
b11001 (
#255
1"
#260
b11001 &
b11001 +
b11001 %
b11001 *
0"
b11010 (
#265
1"
#270
b11010 &
b11010 +
b11010 %
b11010 *
0"
b11011 (
#275
1"
#280
b11011 &
b11011 +
b11011 %
b11011 *
0"
b11100 (
#285
1"
#290
b11100 &
b11100 +
b11100 %
b11100 *
0"
b11101 (
#295
1"
#300
b11101 &
b11101 +
b11101 %
b11101 *
0"
b11110 (
#305
1"
#310
b11110 &
b11110 +
b11110 %
b11110 *
0"
b11111 (
#315
1"
#320
b11111 &
b11111 +
b11111 %
b11111 *
0"
b100000 (
#325
1"
#330
b100000 &
b100000 +
b100000 %
b100000 *
0"
b100001 (
#335
1"
#340
b100001 &
b100001 +
b100001 %
b100001 *
0"
b100010 (
#345
1"
#350
b100010 &
b100010 +
b100010 %
b100010 *
0"
b100011 (
#355
1"
#360
b100011 &
b100011 +
b100011 %
b100011 *
0"
b100100 (
#365
1"
#370
b100100 &
b100100 +
b100100 %
b100100 *
0"
b100101 (
#375
1"
#380
b100101 &
b100101 +
b100101 %
b100101 *
0"
b100110 (
#385
1"
#390
b100110 &
b100110 +
b100110 %
b100110 *
0"
b100111 (
#395
1"
#400
b100111 &
b100111 +
b100111 %
b100111 *
0"
b101000 (
#405
1"
#410
b101000 &
b101000 +
b101000 %
b101000 *
0"
b101001 (
#415
1"
#420
b101001 &
b101001 +
b101001 %
b101001 *
0"
b101010 (
#425
1"
#430
b101010 &
b101010 +
b101010 %
b101010 *
0"
b101011 (
#435
1"
#440
b101011 &
b101011 +
b101011 %
b101011 *
0"
b101100 (
#445
1"
#450
b101100 &
b101100 +
b101100 %
b101100 *
0"
b101101 (
#455
1"
#460
b101101 &
b101101 +
b101101 %
b101101 *
0"
b101110 (
#465
1"
#470
b101110 &
b101110 +
b101110 %
b101110 *
0"
b101111 (
#475
1"
#480
b101111 &
b101111 +
b101111 %
b101111 *
0"
b110000 (
#485
1"
#490
b110000 &
b110000 +
b110000 %
b110000 *
0"
b110001 (
#495
1"
#500
b110001 &
b110001 +
b110001 %
b110001 *
0"
b110010 (
#505
1"
#510
b110010 &
b110010 +
b110010 %
b110010 *
0"
b110011 (
#515
1"
#520
b110011 &
b110011 +
b110011 %
b110011 *
0"
b110100 (
#525
1"
#530
b110100 &
b110100 +
b110100 %
b110100 *
0"
b110101 (
#535
1"
#540
b110101 &
b110101 +
b110101 %
b110101 *
0"
b110110 (
#545
1"
#550
b110110 &
b110110 +
b110110 %
b110110 *
0"
b110111 (
#555
1"
#560
b110111 &
b110111 +
b110111 %
b110111 *
0"
b111000 (
#565
1"
#570
b111000 &
b111000 +
b111000 %
b111000 *
0"
b111001 (
#575
1"
#580
b111001 &
b111001 +
b111001 %
b111001 *
0"
b111010 (
#585
1"
#590
b111010 &
b111010 +
b111010 %
b111010 *
0"
b111011 (
#595
1"
#600
b111011 &
b111011 +
b111011 %
b111011 *
0"
b111100 (
#605
1"
#610
b111100 &
b111100 +
b111100 %
b111100 *
0"
b111101 (
#615
1"
#620
b111101 &
b111101 +
b111101 %
b111101 *
0"
b111110 (
#625
1"
#630
b111110 &
b111110 +
b111110 %
b111110 *
0"
b111111 (
#635
1"
#640
b0 #
b0 )
1$
0'
b111111 &
b111111 +
b111111 %
b111111 *
0"
b0 (
#645
1-
b0 .
1"
#650
b1 #
b1 )
0"
b1 (
#655
b1 .
1"
#660
b10 #
b10 )
0"
b10 (
#665
b10 .
b1 !
b1 ,
1"
#670
b11 #
b11 )
0"
b11 (
#675
b11 .
b10 !
b10 ,
1"
#680
b100 #
b100 )
0"
b100 (
#685
b100 .
b11 !
b11 ,
1"
#690
b101 #
b101 )
0"
b101 (
#695
b101 .
b100 !
b100 ,
1"
#700
b110 #
b110 )
0"
b110 (
#705
b110 .
b101 !
b101 ,
1"
#710
b111 #
b111 )
0"
b111 (
#715
b111 .
b110 !
b110 ,
1"
#720
b1000 #
b1000 )
0"
b1000 (
#725
b1000 .
b111 !
b111 ,
1"
#730
b1001 #
b1001 )
0"
b1001 (
#735
b1001 .
b1000 !
b1000 ,
1"
#740
b1010 #
b1010 )
0"
b1010 (
#745
b1010 .
b1001 !
b1001 ,
1"
#750
b1011 #
b1011 )
0"
b1011 (
#755
b1011 .
b1010 !
b1010 ,
1"
#760
b1100 #
b1100 )
0"
b1100 (
#765
b1100 .
b1011 !
b1011 ,
1"
#770
b1101 #
b1101 )
0"
b1101 (
#775
b1101 .
b1100 !
b1100 ,
1"
#780
b1110 #
b1110 )
0"
b1110 (
#785
b1110 .
b1101 !
b1101 ,
1"
#790
b1111 #
b1111 )
0"
b1111 (
#795
b1111 .
b1110 !
b1110 ,
1"
#800
b10000 #
b10000 )
0"
b10000 (
#805
b10000 .
b1111 !
b1111 ,
1"
#810
b10001 #
b10001 )
0"
b10001 (
#815
b10001 .
b10000 !
b10000 ,
1"
#820
b10010 #
b10010 )
0"
b10010 (
#825
b10010 .
b10001 !
b10001 ,
1"
#830
b10011 #
b10011 )
0"
b10011 (
#835
b10011 .
b10010 !
b10010 ,
1"
#840
b10100 #
b10100 )
0"
b10100 (
#845
b10100 .
b10011 !
b10011 ,
1"
#850
b10101 #
b10101 )
0"
b10101 (
#855
b10101 .
b10100 !
b10100 ,
1"
#860
b10110 #
b10110 )
0"
b10110 (
#865
b10110 .
b10101 !
b10101 ,
1"
#870
b10111 #
b10111 )
0"
b10111 (
#875
b10111 .
b10110 !
b10110 ,
1"
#880
b11000 #
b11000 )
0"
b11000 (
#885
b11000 .
b10111 !
b10111 ,
1"
#890
b11001 #
b11001 )
0"
b11001 (
#895
b11001 .
b11000 !
b11000 ,
1"
#900
b11010 #
b11010 )
0"
b11010 (
#905
b11010 .
b11001 !
b11001 ,
1"
#910
b11011 #
b11011 )
0"
b11011 (
#915
b11011 .
b11010 !
b11010 ,
1"
#920
b11100 #
b11100 )
0"
b11100 (
#925
b11100 .
b11011 !
b11011 ,
1"
#930
b11101 #
b11101 )
0"
b11101 (
#935
b11101 .
b11100 !
b11100 ,
1"
#940
b11110 #
b11110 )
0"
b11110 (
#945
b11110 .
b11101 !
b11101 ,
1"
#950
b11111 #
b11111 )
0"
b11111 (
#955
b11111 .
b11110 !
b11110 ,
1"
#960
b100000 #
b100000 )
0"
b100000 (
#965
b100000 .
b11111 !
b11111 ,
1"
#970
b100001 #
b100001 )
0"
b100001 (
#975
b100001 .
b100000 !
b100000 ,
1"
#980
b100010 #
b100010 )
0"
b100010 (
#985
b100010 .
b100001 !
b100001 ,
1"
#990
b100011 #
b100011 )
0"
b100011 (
#995
b100011 .
b100010 !
b100010 ,
1"
#1000
b100100 #
b100100 )
0"
b100100 (
#1005
b100100 .
b100011 !
b100011 ,
1"
#1010
b100101 #
b100101 )
0"
b100101 (
#1015
b100101 .
b100100 !
b100100 ,
1"
#1020
b100110 #
b100110 )
0"
b100110 (
#1025
b100110 .
b100101 !
b100101 ,
1"
#1030
b100111 #
b100111 )
0"
b100111 (
#1035
b100111 .
b100110 !
b100110 ,
1"
#1040
b101000 #
b101000 )
0"
b101000 (
#1045
b101000 .
b100111 !
b100111 ,
1"
#1050
b101001 #
b101001 )
0"
b101001 (
#1055
b101001 .
b101000 !
b101000 ,
1"
#1060
b101010 #
b101010 )
0"
b101010 (
#1065
b101010 .
b101001 !
b101001 ,
1"
#1070
b101011 #
b101011 )
0"
b101011 (
#1075
b101011 .
b101010 !
b101010 ,
1"
#1080
b101100 #
b101100 )
0"
b101100 (
#1085
b101100 .
b101011 !
b101011 ,
1"
#1090
b101101 #
b101101 )
0"
b101101 (
#1095
b101101 .
b101100 !
b101100 ,
1"
#1100
b101110 #
b101110 )
0"
b101110 (
#1105
b101110 .
b101101 !
b101101 ,
1"
#1110
b101111 #
b101111 )
0"
b101111 (
#1115
b101111 .
b101110 !
b101110 ,
1"
#1120
b110000 #
b110000 )
0"
b110000 (
#1125
b110000 .
b101111 !
b101111 ,
1"
#1130
b110001 #
b110001 )
0"
b110001 (
#1135
b110001 .
b110000 !
b110000 ,
1"
#1140
b110010 #
b110010 )
0"
b110010 (
#1145
b110010 .
b110001 !
b110001 ,
1"
#1150
b110011 #
b110011 )
0"
b110011 (
#1155
b110011 .
b110010 !
b110010 ,
1"
#1160
b110100 #
b110100 )
0"
b110100 (
#1165
b110100 .
b110011 !
b110011 ,
1"
#1170
b110101 #
b110101 )
0"
b110101 (
#1175
b110101 .
b110100 !
b110100 ,
1"
#1180
b110110 #
b110110 )
0"
b110110 (
#1185
b110110 .
b110101 !
b110101 ,
1"
#1190
b110111 #
b110111 )
0"
b110111 (
#1195
b110111 .
b110110 !
b110110 ,
1"
#1200
b111000 #
b111000 )
0"
b111000 (
#1205
b111000 .
b110111 !
b110111 ,
1"
#1210
b111001 #
b111001 )
0"
b111001 (
#1215
b111001 .
b111000 !
b111000 ,
1"
#1220
b111010 #
b111010 )
0"
b111010 (
#1225
b111010 .
b111001 !
b111001 ,
1"
#1230
b111011 #
b111011 )
0"
b111011 (
#1235
b111011 .
b111010 !
b111010 ,
1"
#1240
b111100 #
b111100 )
0"
b111100 (
#1245
b111100 .
b111011 !
b111011 ,
1"
#1250
b111101 #
b111101 )
0"
b111101 (
#1255
b111101 .
b111100 !
b111100 ,
1"
#1260
b111110 #
b111110 )
0"
b111110 (
#1265
b111110 .
b111101 !
b111101 ,
1"
#1270
b111111 #
b111111 )
0"
b111111 (
#1275
bx .
b111110 !
b111110 ,
1"
#1280
0"
b1000000 (
#1285
bx !
bx ,
1"
#1290
0$
0"
#1295
0-
1"
#1300
0"
#1305
b0 !
b0 ,
1"
