myLab/mul_simple.v
module mul_simple #(    //алгоритм умножения столбиком
    parameter DATA_1_WIDTH = 8,
    parameter DATA_2_WIDTH = DATA_1_WIDTH,
    parameter RES_WIDTH = DATA_1_WIDTH + DATA_2_WIDTH
)(
    input wire [DATA_1_WIDTH - 1 : 0] first,
    input wire [DATA_2_WIDTH - 1 : 0] second,
    output wire [RES_WIDTH - 1 : 0] result
);
    wire [RES_WIDTH - 1 : 0] first_byte_extended;
    assign first_byte_extended = {{(RES_WIDTH - DATA_1_WIDTH){1'b0}}, first[DATA_1_WIDTH - 1 : 0]};

    wire [RES_WIDTH - 1 : 0] mul_by_digit [DATA_2_WIDTH - 1 : 0];
    genvar i;
    generate for(i = 0; i < DATA_2_WIDTH; i = i + 1) begin : loop_mul
        assign mul_by_digit[i] = (first_byte_extended << i) & {RES_WIDTH{second[i]}};
    end
    endgenerate

    wire [RES_WIDTH - 1 : 0] mid_data [DATA_2_WIDTH - 1 : 0];
    generate for(i = 0; i < DATA_2_WIDTH; i = i + 1) begin : loop_sum
        if(i == 0)
            assign mid_data[i] = mul_by_digit[i];
        else
            assign mid_data[i] = mid_data[i - 1] + mul_by_digit[i]; // сумматоры - опасно, могут возникать задержки
    end
    endgenerate

    assign result = mid_data[DATA_2_WIDTH - 1];

endmodule

myLab/mul.v
`include "mul_simple.v"

module mul #( //unsigned случай
    parameter DATA_WIDTH = 32,
    parameter RES_WIDTH = DATA_WIDTH * 2,
    parameter PART_DATA_WIDTH = 8
)(
    input wire clk,
    input wire reset,
    input wire rd_en,
    input wire wr_en,
    input wire [DATA_WIDTH - 1 : 0] wr_data_1,  //чет нельзя массивом, icarus требует "SystemVerilog support"
    input wire [DATA_WIDTH - 1 : 0] wr_data_2,
    output wire [RES_WIDTH - 1 : 0] rd_data,
    output reg wr_ready,
    output reg rd_ready,
    output reg rd_val
);
    reg [DATA_WIDTH - 1 : 0] wr_data_1_save;
    reg [DATA_WIDTH - 1 : 0] wr_data_2_save;
    reg [RES_WIDTH - 1 : 0] result;

    localparam EXT_WIDTH = DATA_WIDTH + DATA_WIDTH % PART_DATA_WIDTH;
    wire [EXT_WIDTH - 1 : 0] wr_data_2_save_extended;
    generate if(EXT_WIDTH == DATA_WIDTH) begin : gen_if_ext
        assign wr_data_2_save_extended = wr_data_2_save;
    end
    else begin
        assign wr_data_2_save_extended = {{(EXT_WIDTH - DATA_WIDTH){1'b0}}, wr_data_2_save[DATA_WIDTH - 1 : 0]};
    end //возможно не стоило так перебарщивать с параметризацией, но уже поздно
    endgenerate

    localparam STEP_COUNT = EXT_WIDTH / PART_DATA_WIDTH;
    localparam STEP_WIDTH = $clog2(STEP_COUNT);
    reg [STEP_WIDTH- 1 : 0] step;

    wire [PART_DATA_WIDTH - 1 : 0] part_second [STEP_COUNT - 1 : 0];
    genvar i;
    generate for(i = 0; i < STEP_COUNT; i = i + 1) begin : loop_parts
        assign part_second[i] = wr_data_2_save_extended[PART_DATA_WIDTH * (i + 1) - 1 : PART_DATA_WIDTH * i];
    end
    endgenerate

    localparam PART_RES_WIDTH = RES_WIDTH;
    wire [PART_RES_WIDTH - 1 : 0] part_res;

    mul_simple #(.DATA_1_WIDTH(DATA_WIDTH), .DATA_2_WIDTH(PART_DATA_WIDTH), .RES_WIDTH(PART_RES_WIDTH)) mul_simple_main
               (wr_data_1_save, part_second[step], part_res);

    localparam STEP_MUL_PDW_WIDTH = $clog2(STEP_COUNT * PART_DATA_WIDTH); //равнозначно - $clog2(EXT_WIDTH)
    wire [STEP_MUL_PDW_WIDTH - 1 : 0] step_mul_PDW;

    //я запрещаю умножать
    mul_simple #(.DATA_1_WIDTH(STEP_WIDTH), .DATA_2_WIDTH($clog2(PART_DATA_WIDTH + 1)), .RES_WIDTH(STEP_MUL_PDW_WIDTH))
        mul_simple_step (step, PART_DATA_WIDTH [$clog2(PART_DATA_WIDTH + 1) - 1 : 0], step_mul_PDW);

    assign rd_data = result;

    always @(posedge clk)
        if(reset)
            wr_ready <= 1;
        else
            wr_ready <= (wr_en) ? 0 :
                (rd_en & rd_ready) ? 1 : wr_ready;

    always @(posedge clk)
        if(reset)
            rd_ready <= 0;
        else
            rd_ready <= (rd_en) ? 0 :
                (step == STEP_COUNT - 1) ? 1 : rd_ready;

    always @(posedge clk) begin
        if(reset) begin
            wr_data_1_save <= 0;
            wr_data_2_save <= 0;
        end
        else begin
            wr_data_1_save <= (wr_en & wr_ready) ? wr_data_1 : wr_data_1_save;
            wr_data_2_save <= (wr_en & wr_ready) ? wr_data_2 : wr_data_2_save;
        end
    end

    always @(posedge clk)
        if(reset)
            step <= 0;
        else
            step <= (step == STEP_COUNT - 1) ? 0 :
                (~wr_ready) ? step + 1 : step;

    always @(posedge clk)
        if(reset)
            result <= 0;
        else
            result <= (~rd_ready & ~wr_ready) ? result + ((part_res) << step_mul_PDW) : result;

    always @(posedge clk)
        if(reset)
            rd_val <= 0;
        else
            rd_val <= (rd_en) ? rd_ready : rd_val;

endmodule

myLab/test.v
`include "mul.v"

module test;

    reg clk = 1;
    always #5 clk = ~clk;

    localparam DATA_WIDTH = 32;
    localparam RES_WIDTH = DATA_WIDTH * 2;
    localparam PART_DATA_WIDTH = 8;

    reg reset;
    reg rd_en;
    reg wr_en;
    reg [DATA_WIDTH - 1 : 0] wr_data_1;
    reg [DATA_WIDTH - 1 : 0] wr_data_2;
    wire [RES_WIDTH - 1 : 0] rd_data;
    wire wr_ready;
    wire rd_ready;
    wire rd_val;

    mul #(.DATA_WIDTH(DATA_WIDTH), .RES_WIDTH(RES_WIDTH), .PART_DATA_WIDTH(PART_DATA_WIDTH))
        mul1 (clk, reset, rd_en, wr_en, wr_data_1, wr_data_2, rd_data, wr_ready, rd_ready, rd_val);

    initial begin
        wr_en <= 0;
        rd_en <= 0;
        reset <= 1;
        #10 reset <= 0;
        wr_en <= 1;
        wr_data_1 <= 32'h123456;
        wr_data_2 <= 32'h123456;
        #10 wr_en <= 0;
    end
    //dump settings
    initial begin
        $monitor(rd_data, " ", rd_ready, " ", rd_val);
    end

    initial begin
        $dumpfile("test.vcd");
        $dumpvars(2, test);
    end

    initial begin
        #2000 $finish();
    end

endmodule

myLab/test.vcd
$date
	Tue Jul 18 18:51:08 2023
$end
$version
	Icarus Verilog
$end
$timescale
	1s
$end
$scope module test $end
$var wire 1 ! wr_ready $end
$var wire 1 " rd_val $end
$var wire 1 # rd_ready $end
$var wire 64 $ rd_data [63:0] $end
$var reg 1 % clk $end
$var reg 1 & rd_en $end
$var reg 1 ' reset $end
$var reg 32 ( wr_data_1 [31:0] $end
$var reg 32 ) wr_data_2 [31:0] $end
$var reg 1 * wr_en $end
$scope module mul1 $end
$var wire 1 % clk $end
$var wire 64 + rd_data [63:0] $end
$var wire 1 & rd_en $end
$var wire 1 ' reset $end
$var wire 32 , wr_data_1 [31:0] $end
$var wire 32 - wr_data_2 [31:0] $end
$var wire 32 . wr_data_2_save_extended [31:0] $end
$var wire 1 * wr_en $end
$var wire 5 / step_mul_PDW [4:0] $end
$var wire 64 0 part_res [63:0] $end
$var reg 1 # rd_ready $end
$var reg 1 " rd_val $end
$var reg 64 1 result [63:0] $end
$var reg 2 2 step [1:0] $end
$var reg 32 3 wr_data_1_save [31:0] $end
$var reg 32 4 wr_data_2_save [31:0] $end
$var reg 1 ! wr_ready $end
$upscope $end
$upscope $end
$enddefinitions $end
#0
$dumpvars
bx 4
bx 3
bx 2
bx 1
bx 0
bx /
bx .
bx -
bx ,
bx +
0*
bx )
bx (
1'
0&
1%
bx $
x#
x"
x!
$end
#5
0%
#10
b0 /
b0 0
0"
b0 $
b0 +
b0 1
b0 2
b0 .
b0 4
b0 3
0#
1!
b100100011010001010110 )
b100100011010001010110 -
b100100011010001010110 (
b100100011010001010110 ,
1*
0'
1%
#15
0%
#20
b110000111011001010011100100 0
0!
b100100011010001010110 .
b100100011010001010110 4
b100100011010001010110 3
0*
1%
#25
0%
#30
b11101100101010000101111000 0
b1000 /
b110000111011001010011100100 $
b110000111011001010011100100 +
b110000111011001010011100100 1
b1 2
1%
#35
0%
#40
b1010001111010111000001100 0
b10000 /
b10 2
b1110111000101111110000110011100100 $
b1110111000101111110000110011100100 +
b1110111000101111110000110011100100 1
1%
#45
0%
#50
b0 0
b11000 /
b10100101101100110110010110000110011100100 $
b10100101101100110110010110000110011100100 +
b10100101101100110110010110000110011100100 1
b11 2
1%
#55
0%
#60
b110000111011001010011100100 0
b0 /
1#
b0 2
1%
#65
0%
#70
b11101100101010000101111000 0
b1000 /
b1 2
1%
#75
0%
#80
b1010001111010111000001100 0
b10000 /
b10 2
1%
#85
0%
#90
b0 0
b11000 /
b11 2
1%
#95
0%
#100
b110000111011001010011100100 0
b0 /
b0 2
1%
#105
0%
#110
b11101100101010000101111000 0
b1000 /
b1 2
1%
#115
0%
#120
b1010001111010111000001100 0
b10000 /
b10 2
1%
#125
0%
#130
b0 0
b11000 /
b11 2
1%
#135
0%
#140
b110000111011001010011100100 0
b0 /
b0 2
1%
#145
0%
#150
b11101100101010000101111000 0
b1000 /
b1 2
1%
#155
0%
#160
b1010001111010111000001100 0
b10000 /
b10 2
1%
#165
0%
#170
b0 0
b11000 /
b11 2
1%
#175
0%
#180
b110000111011001010011100100 0
b0 /
b0 2
1%
#185
0%
#190
b11101100101010000101111000 0
b1000 /
b1 2
1%
#195
0%
#200
b1010001111010111000001100 0
b10000 /
b10 2
1%
#205
0%
#210
b0 0
b11000 /
b11 2
1%
#215
0%
#220
b110000111011001010011100100 0
b0 /
b0 2
1%
#225
0%
#230
b11101100101010000101111000 0
b1000 /
b1 2
1%
#235
0%
#240
b1010001111010111000001100 0
b10000 /
b10 2
1%
#245
0%
#250
b0 0
b11000 /
b11 2
1%
#255
0%
#260
b110000111011001010011100100 0
b0 /
b0 2
1%
#265
0%
#270
b11101100101010000101111000 0
b1000 /
b1 2
1%
#275
0%
#280
b1010001111010111000001100 0
b10000 /
b10 2
1%
#285
0%
#290
b0 0
b11000 /
b11 2
1%
#295
0%
#300
b110000111011001010011100100 0
b0 /
b0 2
1%
#305
0%
#310
b11101100101010000101111000 0
b1000 /
b1 2
1%
#315
0%
#320
b1010001111010111000001100 0
b10000 /
b10 2
1%
#325
0%
#330
b0 0
b11000 /
b11 2
1%
#335
0%
#340
b110000111011001010011100100 0
b0 /
b0 2
1%
#345
0%
#350
b11101100101010000101111000 0
b1000 /
b1 2
1%
#355
0%
#360
b1010001111010111000001100 0
b10000 /
b10 2
1%
#365
0%
#370
b0 0
b11000 /
b11 2
1%
#375
0%
#380
b110000111011001010011100100 0
b0 /
b0 2
1%
#385
0%
#390
b11101100101010000101111000 0
b1000 /
b1 2
1%
#395
0%
#400
b1010001111010111000001100 0
b10000 /
b10 2
1%
#405
0%
#410
b0 0
b11000 /
b11 2
1%
#415
0%
#420
b110000111011001010011100100 0
b0 /
b0 2
1%
#425
0%
#430
b11101100101010000101111000 0
b1000 /
b1 2
1%
#435
0%
#440
b1010001111010111000001100 0
b10000 /
b10 2
1%
#445
0%
#450
b0 0
b11000 /
b11 2
1%
#455
0%
#460
b110000111011001010011100100 0
b0 /
b0 2
1%
#465
0%
#470
b11101100101010000101111000 0
b1000 /
b1 2
1%
#475
0%
#480
b1010001111010111000001100 0
b10000 /
b10 2
1%
#485
0%
#490
b0 0
b11000 /
b11 2
1%
#495
0%
#500
b110000111011001010011100100 0
b0 /
b0 2
1%
#505
0%
#510
b11101100101010000101111000 0
b1000 /
b1 2
1%
#515
0%
#520
b1010001111010111000001100 0
b10000 /
b10 2
1%
#525
0%
#530
b0 0
b11000 /
b11 2
1%
#535
0%
#540
b110000111011001010011100100 0
b0 /
b0 2
1%
#545
0%
#550
b11101100101010000101111000 0
b1000 /
b1 2
1%
#555
0%
#560
b1010001111010111000001100 0
b10000 /
b10 2
1%
#565
0%
#570
b0 0
b11000 /
b11 2
1%
#575
0%
#580
b110000111011001010011100100 0
b0 /
b0 2
1%
#585
0%
#590
b11101100101010000101111000 0
b1000 /
b1 2
1%
#595
0%
#600
b1010001111010111000001100 0
b10000 /
b10 2
1%
#605
0%
#610
b0 0
b11000 /
b11 2
1%
#615
0%
#620
b110000111011001010011100100 0
b0 /
b0 2
1%
#625
0%
#630
b11101100101010000101111000 0
b1000 /
b1 2
1%
#635
0%
#640
b1010001111010111000001100 0
b10000 /
b10 2
1%
#645
0%
#650
b0 0
b11000 /
b11 2
1%
#655
0%
#660
b110000111011001010011100100 0
b0 /
b0 2
1%
#665
0%
#670
b11101100101010000101111000 0
b1000 /
b1 2
1%
#675
0%
#680
b1010001111010111000001100 0
b10000 /
b10 2
1%
#685
0%
#690
b0 0
b11000 /
b11 2
1%
#695
0%
#700
b110000111011001010011100100 0
b0 /
b0 2
1%
#705
0%
#710
b11101100101010000101111000 0
b1000 /
b1 2
1%
#715
0%
#720
b1010001111010111000001100 0
b10000 /
b10 2
1%
#725
0%
#730
b0 0
b11000 /
b11 2
1%
#735
0%
#740
b110000111011001010011100100 0
b0 /
b0 2
1%
#745
0%
#750
b11101100101010000101111000 0
b1000 /
b1 2
1%
#755
0%
#760
b1010001111010111000001100 0
b10000 /
b10 2
1%
#765
0%
#770
b0 0
b11000 /
b11 2
1%
#775
0%
#780
b110000111011001010011100100 0
b0 /
b0 2
1%
#785
0%
#790
b11101100101010000101111000 0
b1000 /
b1 2
1%
#795
0%
#800
b1010001111010111000001100 0
b10000 /
b10 2
1%
#805
0%
#810
b0 0
b11000 /
b11 2
1%
#815
0%
#820
b110000111011001010011100100 0
b0 /
b0 2
1%
#825
0%
#830
b11101100101010000101111000 0
b1000 /
b1 2
1%
#835
0%
#840
b1010001111010111000001100 0
b10000 /
b10 2
1%
#845
0%
#850
b0 0
b11000 /
b11 2
1%
#855
0%
#860
b110000111011001010011100100 0
b0 /
b0 2
1%
#865
0%
#870
b11101100101010000101111000 0
b1000 /
b1 2
1%
#875
0%
#880
b1010001111010111000001100 0
b10000 /
b10 2
1%
#885
0%
#890
b0 0
b11000 /
b11 2
1%
#895
0%
#900
b110000111011001010011100100 0
b0 /
b0 2
1%
#905
0%
#910
b11101100101010000101111000 0
b1000 /
b1 2
1%
#915
0%
#920
b1010001111010111000001100 0
b10000 /
b10 2
1%
#925
0%
#930
b0 0
b11000 /
b11 2
1%
#935
0%
#940
b110000111011001010011100100 0
b0 /
b0 2
1%
#945
0%
#950
b11101100101010000101111000 0
b1000 /
b1 2
1%
#955
0%
#960
b1010001111010111000001100 0
b10000 /
b10 2
1%
#965
0%
#970
b0 0
b11000 /
b11 2
1%
#975
0%
#980
b110000111011001010011100100 0
b0 /
b0 2
1%
#985
0%
#990
b11101100101010000101111000 0
b1000 /
b1 2
1%
#995
0%
#1000
b1010001111010111000001100 0
b10000 /
b10 2
1%
#1005
0%
#1010
b0 0
b11000 /
b11 2
1%
#1015
0%
#1020
b110000111011001010011100100 0
b0 /
b0 2
1%
#1025
0%
#1030
b11101100101010000101111000 0
b1000 /
b1 2
1%
#1035
0%
#1040
b1010001111010111000001100 0
b10000 /
b10 2
1%
#1045
0%
#1050
b0 0
b11000 /
b11 2
1%
#1055
0%
#1060
b110000111011001010011100100 0
b0 /
b0 2
1%
#1065
0%
#1070
b11101100101010000101111000 0
b1000 /
b1 2
1%
#1075
0%
#1080
b1010001111010111000001100 0
b10000 /
b10 2
1%
#1085
0%
#1090
b0 0
b11000 /
b11 2
1%
#1095
0%
#1100
b110000111011001010011100100 0
b0 /
b0 2
1%
#1105
0%
#1110
b11101100101010000101111000 0
b1000 /
b1 2
1%
#1115
0%
#1120
b1010001111010111000001100 0
b10000 /
b10 2
1%
#1125
0%
#1130
b0 0
b11000 /
b11 2
1%
#1135
0%
#1140
b110000111011001010011100100 0
b0 /
b0 2
1%
#1145
0%
#1150
b11101100101010000101111000 0
b1000 /
b1 2
1%
#1155
0%
#1160
b1010001111010111000001100 0
b10000 /
b10 2
1%
#1165
0%
#1170
b0 0
b11000 /
b11 2
1%
#1175
0%
#1180
b110000111011001010011100100 0
b0 /
b0 2
1%
#1185
0%
#1190
b11101100101010000101111000 0
b1000 /
b1 2
1%
#1195
0%
#1200
b1010001111010111000001100 0
b10000 /
b10 2
1%
#1205
0%
#1210
b0 0
b11000 /
b11 2
1%
#1215
0%
#1220
b110000111011001010011100100 0
b0 /
b0 2
1%
#1225
0%
#1230
b11101100101010000101111000 0
b1000 /
b1 2
1%
#1235
0%
#1240
b1010001111010111000001100 0
b10000 /
b10 2
1%
#1245
0%
#1250
b0 0
b11000 /
b11 2
1%
#1255
0%
#1260
b110000111011001010011100100 0
b0 /
b0 2
1%
#1265
0%
#1270
b11101100101010000101111000 0
b1000 /
b1 2
1%
#1275
0%
#1280
b1010001111010111000001100 0
b10000 /
b10 2
1%
#1285
0%
#1290
b0 0
b11000 /
b11 2
1%
#1295
0%
#1300
b110000111011001010011100100 0
b0 /
b0 2
1%
#1305
0%
#1310
b11101100101010000101111000 0
b1000 /
b1 2
1%
#1315
0%
#1320
b1010001111010111000001100 0
b10000 /
b10 2
1%
#1325
0%
#1330
b0 0
b11000 /
b11 2
1%
#1335
0%
#1340
b110000111011001010011100100 0
b0 /
b0 2
1%
#1345
0%
#1350
b11101100101010000101111000 0
b1000 /
b1 2
1%
#1355
0%
#1360
b1010001111010111000001100 0
b10000 /
b10 2
1%
#1365
0%
#1370
b0 0
b11000 /
b11 2
1%
#1375
0%
#1380
b110000111011001010011100100 0
b0 /
b0 2
1%
#1385
0%
#1390
b11101100101010000101111000 0
b1000 /
b1 2
1%
#1395
0%
#1400
b1010001111010111000001100 0
b10000 /
b10 2
1%
#1405
0%
#1410
b0 0
b11000 /
b11 2
1%
#1415
0%
#1420
b110000111011001010011100100 0
b0 /
b0 2
1%
#1425
0%
#1430
b11101100101010000101111000 0
b1000 /
b1 2
1%
#1435
0%
#1440
b1010001111010111000001100 0
b10000 /
b10 2
1%
#1445
0%
#1450
b0 0
b11000 /
b11 2
1%
#1455
0%
#1460
b110000111011001010011100100 0
b0 /
b0 2
1%
#1465
0%
#1470
b11101100101010000101111000 0
b1000 /
b1 2
1%
#1475
0%
#1480
b1010001111010111000001100 0
b10000 /
b10 2
1%
#1485
0%
#1490
b0 0
b11000 /
b11 2
1%
#1495
0%
#1500
b110000111011001010011100100 0
b0 /
b0 2
1%
#1505
0%
#1510
b11101100101010000101111000 0
b1000 /
b1 2
1%
#1515
0%
#1520
b1010001111010111000001100 0
b10000 /
b10 2
1%
#1525
0%
#1530
b0 0
b11000 /
b11 2
1%
#1535
0%
#1540
b110000111011001010011100100 0
b0 /
b0 2
1%
#1545
0%
#1550
b11101100101010000101111000 0
b1000 /
b1 2
1%
#1555
0%
#1560
b1010001111010111000001100 0
b10000 /
b10 2
1%
#1565
0%
#1570
b0 0
b11000 /
b11 2
1%
#1575
0%
#1580
b110000111011001010011100100 0
b0 /
b0 2
1%
#1585
0%
#1590
b11101100101010000101111000 0
b1000 /
b1 2
1%
#1595
0%
#1600
b1010001111010111000001100 0
b10000 /
b10 2
1%
#1605
0%
#1610
b0 0
b11000 /
b11 2
1%
#1615
0%
#1620
b110000111011001010011100100 0
b0 /
b0 2
1%
#1625
0%
#1630
b11101100101010000101111000 0
b1000 /
b1 2
1%
#1635
0%
#1640
b1010001111010111000001100 0
b10000 /
b10 2
1%
#1645
0%
#1650
b0 0
b11000 /
b11 2
1%
#1655
0%
#1660
b110000111011001010011100100 0
b0 /
b0 2
1%
#1665
0%
#1670
b11101100101010000101111000 0
b1000 /
b1 2
1%
#1675
0%
#1680
b1010001111010111000001100 0
b10000 /
b10 2
1%
#1685
0%
#1690
b0 0
b11000 /
b11 2
1%
#1695
0%
#1700
b110000111011001010011100100 0
b0 /
b0 2
1%
#1705
0%
#1710
b11101100101010000101111000 0
b1000 /
b1 2
1%
#1715
0%
#1720
b1010001111010111000001100 0
b10000 /
b10 2
1%
#1725
0%
#1730
b0 0
b11000 /
b11 2
1%
#1735
0%
#1740
b110000111011001010011100100 0
b0 /
b0 2
1%
#1745
0%
#1750
b11101100101010000101111000 0
b1000 /
b1 2
1%
#1755
0%
#1760
b1010001111010111000001100 0
b10000 /
b10 2
1%
#1765
0%
#1770
b0 0
b11000 /
b11 2
1%
#1775
0%
#1780
b110000111011001010011100100 0
b0 /
b0 2
1%
#1785
0%
#1790
b11101100101010000101111000 0
b1000 /
b1 2
1%
#1795
0%
#1800
b1010001111010111000001100 0
b10000 /
b10 2
1%
#1805
0%
#1810
b0 0
b11000 /
b11 2
1%
#1815
0%
#1820
b110000111011001010011100100 0
b0 /
b0 2
1%
#1825
0%
#1830
b11101100101010000101111000 0
b1000 /
b1 2
1%
#1835
0%
#1840
b1010001111010111000001100 0
b10000 /
b10 2
1%
#1845
0%
#1850
b0 0
b11000 /
b11 2
1%
#1855
0%
#1860
b110000111011001010011100100 0
b0 /
b0 2
1%
#1865
0%
#1870
b11101100101010000101111000 0
b1000 /
b1 2
1%
#1875
0%
#1880
b1010001111010111000001100 0
b10000 /
b10 2
1%
#1885
0%
#1890
b0 0
b11000 /
b11 2
1%
#1895
0%
#1900
b110000111011001010011100100 0
b0 /
b0 2
1%
#1905
0%
#1910
b11101100101010000101111000 0
b1000 /
b1 2
1%
#1915
0%
#1920
b1010001111010111000001100 0
b10000 /
b10 2
1%
#1925
0%
#1930
b0 0
b11000 /
b11 2
1%
#1935
0%
#1940
b110000111011001010011100100 0
b0 /
b0 2
1%
#1945
0%
#1950
b11101100101010000101111000 0
b1000 /
b1 2
1%
#1955
0%
#1960
b1010001111010111000001100 0
b10000 /
b10 2
1%
#1965
0%
#1970
b0 0
b11000 /
b11 2
1%
#1975
0%
#1980
b110000111011001010011100100 0
b0 /
b0 2
1%
#1985
0%
#1990
b11101100101010000101111000 0
b1000 /
b1 2
1%
#1995
0%
#2000
b1010001111010111000001100 0
b10000 /
b10 2
1%
